Workbook
Name KPI_Margin: Pivot_Table!$D$4
Name KPI_Profit: Pivot_Table!$C$4
Name KPI_Quantity: Pivot_Table!$E$4
Name KPI_Revenue: Pivot_Table!$B$4
Name ShoeSalesCopy: Table1[]
Name Slicer_Brand_Cleaned: #N/A
Name Slicer_Category_Cleaned: #N/A

Sheet Business Questions
A1: Business Questions:
A3: 1 | B3: How is the business performing overall?
A5: 2 | B5: 2. How have revenue and profit changed over time?
A7: 3 | B7: 3. Which products are driving sales?
A9: 4 | B9: 4. Which products are driving profitability?
A11: 5 | B11: 5. Which categories and brands perform best?
A13: 6 | B13: 6. Which countries contribute the most to the business?
A15: 7 | B15: 7. What purchasing patterns can we identify from payment method and product preferences?
A17: 8 | B17: 8. What actions should management take based on the findings?

Sheet Shoe Sales
B1: Product | C1: Category | D1: Color | E1: Brand | F1: Country | G1: Quantity | H1: Payment Type
A2: 05/19/2026 | B2: monk straps | C2: Formal | D2: Red | E2: Nike | F2: Uganda | G2: 7 | H2: Bank Transfer
A3: 06/26/2026 | B3: loafers | C3: Formal | D3: Black | E3: nike | F3: Uganda | G3: 1 | H3: Card
A4: 05/30/2026 | B4: Derby | C4: FORMAL | D4: Green | E4: clarks | F4: Nigeria | G4: 7 | H4: Bank Transfer
A5: 46333 | B5: boots | C5: UTILITY | D5: Black | E5: nike | F5: Canada | G5: 6 | H5: Bank Transfer
A6: 04/18/2026 | B6: BOOTS | C6: casual | D6: Red | E6: CLARKS | F6: UK | G6: 6 | H6: Bank Transfer
A7: 46359 | B7: Canvas | C7: Utility | D7: Blue | E7: NIKE | F7: Ghana | G7: 6 | H7: Card
A8: 06/18/2026 | B8: canvas | C8: Formal | D8: Green | E8: clarks | F8: USA | G8: 13 | H8: Cash
A9: 46272 | B9: monk straps | C9: Formal | D9: Brown | E9: timberland | F9: USA | G9: 12 | H9: Cash
A10: 01/16/2026 | B10: Derby | C10: formal | D10: Green | E10: clarks | F10: Australia | G10: 10 | H10: Cash
A11: 46271 | B11: OXFORD | C11: Formal | D11: Black | E11: clarks | F11: Cyprus | G11: 15 | H11: Mobile Money
A12: 04/20/2026 | B12: BOOTS | C12: Formal | D12: Brown | E12: Clarks | F12: India | G12: 8 | H12: Bank Transfer
A13: 03/16/2026 | B13: loafers | C13: casual | D13: Green | E13: Clarks | F13: Australia | G13: 9 | H13: Cash
A14: 46117 | B14: BROGUES | C14: UTILITY | D14: Green | E14: Nike | F14: Germany | G14: 14 | H14: Bank Transfer
A15: 46266 | B15: oxford | C15: formal | D15: Green | E15: timberland | F15: Nigeria | G15: 4 | H15: Card
A16: 06/26/2026 | B16: SLIPPERS | C16: FORMAL | D16: Red | E16: ZARA | F16: Uganda | G16: 6 | H16: Card
A17: 07/23/2026 | B17: derby | C17: Casual | D17: Green | E17: Zara | F17: Philippines | G17: 10 | H17: Cash
A18: 04/13/2026 | B18: boots | C18: OPEN | D18: Red | E18: Steve Madden | F18: Nigeria | G18: 7 | H18: Bank Transfer
A19: 05/20/2026 | B19: DERBY | C19: CASUAL | D19: Blue | E19: CLARKS | F19: UK | G19: 7 | H19: Mobile Money
A20: 03/31/2026 | B20: Oxford | C20: OPEN | D20: Black | E20: clarks | F20: UK | G20: 11 | H20: Cash
A21: 46147 | B21: boots | C21: UTILITY | D21: Red | E21: NIKE | F21: Zimbabwe | G21: 6 | H21: Cash
A22: 46211 | B22: Monk Straps | C22: Formal | D22: Red | E22: CLARKS | F22: Germany | G22: 8 | H22: Card
A23: 07/14/2026 | B23: BROGUES | C23: Casual | D23: Green | E23: Steve Madden | F23: Australia | G23: 5 | H23: Mobile Money
A24: 46357 | B24: OXFORD | C24: formal | D24: Green | E24: STEVE MADDEN | F24: Zimbabwe | G24: 15 | H24: Card
A25: 01/28/2026 | B25: Canvas | C25: FORMAL | D25: Green | E25: steve madden | F25: Cyprus | G25: 1 | H25: Card
A26: 01/13/2026 | B26: Boots | C26: CASUAL | D26: Blue | E26: Clarks | F26: Ghana | G26: 12 | H26: Cash
A27: 03/13/2026 | B27: loafers | C27: UTILITY | D27: Green | E27: Steve Madden | F27: India | G27: 9 | H27: Mobile Money
A28: 46333 | B28: oxford | C28: Formal | D28: Green | E28: clarks | F28: Ghana | G28: 5 | H28: Mobile Money
A29: 46298 | B29: loafers | C29: CASUAL | D29: Green | E29: Clarks | F29: Zimbabwe | G29: 8 | H29: Bank Transfer
A30: 04/30/2026 | B30: OXFORD | C30: formal | D30: Red | E30: zara | F30: Nigeria | G30: 2 | H30: Bank Transfer
A31: 02/15/2026 | B31: MONK STRAPS | C31: Formal | D31: Blue | E31: ZARA | F31: Albania | G31: 7 | H31: Cash
A32: 07/16/2026 | B32: brogues | C32: formal | D32: Red | E32: STEVE MADDEN | F32: Germany | G32: 12 | H32: Mobile Money
A33: 46362 | B33: Canvas | C33: formal | D33: Blue | E33: CLARKS | F33: Zimbabwe | G33: 15 | H33: Card
A34: 46061 | B34: boots | C34: FORMAL | D34: Red | E34: Zara | F34: Uganda | G34: 7 | H34: Mobile Money
A35: 03/30/2026 | B35: BROGUES | C35: formal | D35: Black | E35: nike | F35: Cyprus | G35: 10 | H35: Bank Transfer
A36: 04/20/2026 | B36: monk straps | C36: Open | D36: Green | E36: nike | F36: Philippines | G36: 7 | H36: Bank Transfer
A37: 07/25/2026 | B37: boots | C37: formal | D37: Red | E37: timberland | F37: Canada | G37: 5 | H37: Card
A38: 46087 | B38: Boots | C38: FORMAL | D38: Red | E38: Clarks | F38: India | G38: 11 | H38: Bank Transfer
A39: 07/23/2026 | B39: slippers | C39: CASUAL | D39: Red | E39: zara | F39: Zimbabwe | G39: 10 | H39: Bank Transfer
A40: 07/25/2026 | B40: loafers | C40: Open | D40: Green | E40: CLARKS | F40: USA | G40: 10 | H40: Mobile Money
A41: 46087 | B41: OXFORD | C41: Formal | D41: Red | E41: STEVE MADDEN | F41: Germany | G41: 13 | H41: Bank Transfer
A42: 46268 | B42: brogues | C42: formal | D42: Blue | E42: clarks | F42: USA | G42: 7 | H42: Cash
A43: 02/19/2026 | B43: Boots | C43: open | D43: Green | E43: Nike | F43: Nigeria | G43: 14 | H43: Cash
A44: 07/17/2026 | B44: OXFORD | C44: OPEN | D44: Green | E44: CLARKS | F44: Ghana | G44: 13 | H44: Mobile Money
A45: 04/15/2026 | B45: Loafers | C45: Open | D45: Red | E45: Nike | F45: Philippines | G45: 3 | H45: Card
A46: 04/19/2026 | B46: Boots | C46: formal | D46: Green | E46: steve madden | F46: UK | G46: 1 | H46: Bank Transfer
A47: 05/23/2026 | B47: BROGUES | C47: Formal | D47: Red | E47: CLARKS | F47: Germany | G47: 9 | H47: Mobile Money
A48: 46089 | B48: Boots | C48: FORMAL | D48: Green | E48: zara | F48: Albania | G48: 5 | H48: Mobile Money
A49: 46145 | B49: OXFORD | C49: CASUAL | D49: Black | E49: NIKE | F49: USA | G49: 11 | H49: Mobile Money
A50: 03/29/2026 | B50: LOAFERS | C50: formal | D50: Black | E50: zara | F50: USA | G50: 6 | H50: Card
A51: 06/27/2026 | B51: BOOTS | C51: UTILITY | D51: Blue | E51: zara | F51: Kenya | G51: 1 | H51: Mobile Money
A52: 46181 | B52: Canvas | C52: Casual | D52: Red | E52: clarks | F52: Albania | G52: 4 | H52: Bank Transfer
A53: 01/29/2026 | B53: oxford | C53: UTILITY | D53: Black | E53: clarks | F53: India | G53: 5 | H53: Cash
A54: 46145 | B54: monk straps | C54: Formal | D54: Black | E54: zara | F54: Uganda | G54: 4 | H54: Card
A55: 02/16/2026 | B55: brogues | C55: formal | D55: Black | E55: Zara | F55: Nigeria | G55: 1 | H55: Mobile Money
A56: 03/28/2026 | B56: Canvas | C56: formal | D56: Red | E56: nike | F56: Zimbabwe | G56: 4 | H56: Bank Transfer
A57: 46057 | B57: Monk Straps | C57: CASUAL | D57: Black | E57: CLARKS | F57: Canada | G57: 5 | H57: Card
A58: 46059 | B58: CANVAS | C58: OPEN | D58: Black | E58: STEVE MADDEN | F58: Cyprus | G58: 2 | H58: Cash
A59: 01/23/2026 | B59: SLIPPERS | C59: formal | D59: Red | E59: NIKE | F59: Nigeria | G59: 1 | H59: Bank Transfer
A60: 07/27/2026 | B60: BROGUES | C60: Casual | D60: Green | E60: Nike | F60: Uganda | G60: 15 | H60: Bank Transfer
A61: 06/23/2026 | B61: boots | C61: formal | D61: Green | E61: STEVE MADDEN | F61: UK | G61: 11 | H61: Mobile Money
A62: 46269 | B62: Oxford | C62: utility | D62: Red | E62: Clarks | F62: Ghana | G62: 10 | H62: Card
A63: 06/21/2026 | B63: canvas | C63: FORMAL | D63: Brown | E63: STEVE MADDEN | F63: Canada | G63: 9 | H63: Card
A64: 02/28/2026 | B64: Loafers | C64: formal | D64: Blue | E64: nike | F64: Uganda | G64: 1 | H64: Bank Transfer
A65: 06/24/2026 | B65: OXFORD | C65: Formal | D65: Green | E65: ZARA | F65: Cyprus | G65: 8 | H65: Bank Transfer
A66: 03/31/2026 | B66: oxford | C66: CASUAL | D66: Green | E66: STEVE MADDEN | F66: Germany | G66: 5 | H66: Bank Transfer
A67: 46360 | B67: derby | C67: Casual | D67: Black | E67: TIMBERLAND | F67: Nigeria | G67: 14 | H67: Card
A68: 05/19/2026 | B68: MONK STRAPS | C68: OPEN | D68: Brown | E68: clarks | F68: UK | G68: 14 | H68: Mobile Money
A69: 46174 | B69: BROGUES | C69: FORMAL | D69: Black | E69: clarks | F69: Zimbabwe | G69: 8 | H69: Mobile Money
A70: 46179 | B70: Loafers | C70: FORMAL | D70: Black | E70: CLARKS | F70: Philippines | G70: 7 | H70: Bank Transfer
A71: 46271 | B71: brogues | C71: open | D71: Green | E71: clarks | F71: Philippines | G71: 7 | H71: Mobile Money
A72: 46115 | B72: monk straps | C72: Formal | D72: Green | E72: timberland | F72: Ghana | G72: 8 | H72: Cash
A73: 46302 | B73: derby | C73: Casual | D73: Green | E73: Clarks | F73: UK | G73: 9 | H73: Mobile Money
A74: 46237 | B74: boots | C74: FORMAL | D74: Brown | E74: Zara | F74: UK | G74: 5 | H74: Card
A75: 46028 | B75: boots | C75: formal | D75: Blue | E75: STEVE MADDEN | F75: Philippines | G75: 9 | H75: Cash
A76: 02/24/2026 | B76: Oxford | C76: casual | D76: Brown | E76: CLARKS | F76: Germany | G76: 7 | H76: Card
A77: 46178 | B77: Oxford | C77: formal | D77: Green | E77: clarks | F77: Uganda | G77: 13 | H77: Cash
A78: 46144 | B78: LOAFERS | C78: formal | D78: Blue | E78: ZARA | F78: Ghana | G78: 8 | H78: Card
A79: 46084 | B79: DERBY | C79: casual | D79: Brown | E79: timberland | F79: Philippines | G79: 11 | H79: Mobile Money
A80: 04/21/2026 | B80: BROGUES | C80: Formal | D80: Green | E80: CLARKS | F80: Australia | G80: 11 | H80: Card
A81: 07/16/2026 | B81: Slippers | C81: formal | D81: Black | E81: TIMBERLAND | F81: Kenya | G81: 15 | H81: Card
A82: 46268 | B82: Canvas | C82: casual | D82: Brown | E82: Zara | F82: Zimbabwe | G82: 10 | H82: Bank Transfer
A83: 46146 | B83: boots | C83: Utility | D83: Brown | E83: ZARA | F83: Cyprus | G83: 4 | H83: Bank Transfer
A84: 03/16/2026 | B84: BOOTS | C84: Casual | D84: Green | E84: STEVE MADDEN | F84: India | G84: 7 | H84: Mobile Money
A85: 01/19/2026 | B85: Derby | C85: UTILITY | D85: Blue | E85: steve madden | F85: Albania | G85: 7 | H85: Cash
A86: 06/14/2026 | B86: Boots | C86: Formal | D86: Green | E86: ZARA | F86: Nigeria | G86: 13 | H86: Mobile Money
A87: 46058 | B87: Loafers | C87: UTILITY | D87: Green | E87: timberland | F87: Albania | G87: 12 | H87: Bank Transfer
A88: 46114 | B88: BOOTS | C88: casual | D88: Red | E88: TIMBERLAND | F88: Uganda | G88: 14 | H88: Cash
A89: 02/14/2026 | B89: oxford | C89: Formal | D89: Brown | E89: clarks | F89: Albania | G89: 8 | H89: Cash
A90: 03/18/2026 | B90: boots | C90: formal | D90: Green | E90: CLARKS | F90: Cyprus | G90: 3 | H90: Bank Transfer
A91: 46268 | B91: Derby | C91: UTILITY | D91: Black | E91: Steve Madden | F91: Ghana | G91: 8 | H91: Card
A92: 03/30/2026 | B92: Slippers | C92: Utility | D92: Green | E92: zara | F92: Ghana | G92: 14 | H92: Bank Transfer
A93: 46029 | B93: BROGUES | C93: formal | D93: Green | E93: STEVE MADDEN | F93: Nigeria | G93: 7 | H93: Mobile Money
A94: 46364 | B94: LOAFERS | C94: utility | D94: Brown | E94: CLARKS | F94: UK | G94: 5 | H94: Cash
A95: 46327 | B95: Oxford | C95: Formal | D95: Green | E95: STEVE MADDEN | F95: Nigeria | G95: 14 | H95: Cash
A96: 06/30/2026 | B96: slippers | C96: Open | D96: Red | E96: Clarks | F96: USA | G96: 6 | H96: Cash
A97: 01/22/2026 | B97: Slippers | C97: CASUAL | D97: Red | E97: nike | F97: Nigeria | G97: 7 | H97: Card
A98: 07/20/2026 | B98: Loafers | C98: formal | D98: Green | E98: Clarks | F98: Canada | G98: 9 | H98: Bank Transfer
A99: 46177 | B99: monk straps | C99: FORMAL | D99: Blue | E99: Steve Madden | F99: Ghana | G99: 10 | H99: Card
A100: 46357 | B100: brogues | C100: Casual | D100: Red | E100: nike | F100: Zimbabwe | G100: 6 | H100: Card
...

Sheet Shoe_Sales
A1: Date | B1: Year | C1: Day | D1: Month | E1: Product Cleaned | F1: Category Cleaned | G1: Color | H1: Brand Cleaned | I1: Country | J1: Quantity | K1: Payment Type | L1: Selling Price | M1: Cost Price | N1: Total Revenue | O1: Cost | P1: Profit | Q1: Profit Margin
A2: 05/19/2026 | B2: =RIGHT(TRIM(A2), 4) -> 2026 | C2: =MID(TRIM(A2), 4, 2) -> 19 | D2: =TEXT(DATE(RIGHT(TRIM(A2), 4), LEFT(TRIM(A2), 2), MID(TRIM(A2), 4, 2)), "mmm") -> May | E2: Monk Straps | F2: Formal | G2: Red | H2: Nike | I2: Uganda | J2: 7 | K2: Bank Transfer | L2: $89.00 | M2: =VLOOKUP(E2,Price!$A$2:$C$9,3,) -> $47.00 | N2: =J2 * VALUE(SUBSTITUTE(L2,"$","")) -> 623 | O2: =J2*VALUE(SUBSTITUTE(M2,"$","")) -> 329 | P2: =N2-O2 -> 294 | Q2: =Table1[[#This Row],[Profit ]]/Table1[[#This Row],[Total Revenue]] -> 0.47191011
A3: 06/26/2026 | B3: =RIGHT(TRIM(A3), 4) -> 2026 | C3: =MID(TRIM(A3), 4, 2) -> 26 | D3: =TEXT(DATE(RIGHT(TRIM(A3), 4), LEFT(TRIM(A3), 2), MID(TRIM(A3), 4, 2)), "mmm") -> Jun | E3: Loafers | F3: Formal | G3: Black | H3: Nike | I3: Uganda | J3: 1 | K3: Card | L3: $54.00 | M3: =VLOOKUP(E3,Price!$A$2:$C$9,3,) -> $28.00 | N3: =J3 * VALUE(SUBSTITUTE(L3,"$","")) -> 54 | O3: =J3*VALUE(SUBSTITUTE(M3,"$","")) -> 28 | P3: =N3-O3 -> 26 | Q3: =Table1[[#This Row],[Profit ]]/Table1[[#This Row],[Total Revenue]] -> 0.48148148
A4: 05/30/2026 | B4: =RIGHT(TRIM(A4), 4) -> 2026 | C4: =MID(TRIM(A4), 4, 2) -> 30 | D4: =TEXT(DATE(RIGHT(TRIM(A4), 4), LEFT(TRIM(A4), 2), MID(TRIM(A4), 4, 2)), "mmm") -> May | E4: Derby | F4: Formal | G4: Green | H4: Clarks | I4: Nigeria | J4: 7 | K4: Bank Transfer | L4: $32.00 | M4: =VLOOKUP(E4,Price!$A$2:$C$9,3,) -> $14.00 | N4: =J4 * VALUE(SUBSTITUTE(L4,"$","")) -> 224 | O4: =J4*VALUE(SUBSTITUTE(M4,"$","")) -> 98 | P4: =N4-O4 -> 126 | Q4: =Table1[[#This Row],[Profit ]]/Table1[[#This Row],[Total Revenue]] -> 0.5625
A5: 46333 | B5: =RIGHT(TRIM(A5), 4) -> 6333 | C5: =MID(TRIM(A5), 4, 2) -> 33 | D5: =TEXT(DATE(RIGHT(TRIM(A5), 4), LEFT(TRIM(A5), 2), MID(TRIM(A5), 4, 2)), "mmm") -> Nov | E5: Boots | F5: Utility | G5: Black | H5: Nike | I5: Canada | J5: 6 | K5: Bank Transfer | L5: $76.00 | M5: =VLOOKUP(E5,Price!$A$2:$C$9,3,) -> $39.00 | N5: =J5 * VALUE(SUBSTITUTE(L5,"$","")) -> 456 | O5: =J5*VALUE(SUBSTITUTE(M5,"$","")) -> 234 | P5: =N5-O5 -> 222 | Q5: =Table1[[#This Row],[Profit ]]/Table1[[#This Row],[Total Revenue]] -> 0.48684211
A6: 04/18/2026 | B6: =RIGHT(TRIM(A6), 4) -> 2026 | C6: =MID(TRIM(A6), 4, 2) -> 18 | D6: =TEXT(DATE(RIGHT(TRIM(A6), 4), LEFT(TRIM(A6), 2), MID(TRIM(A6), 4, 2)), "mmm") -> Apr | E6: Boots | F6: Casual | G6: Red | H6: Clarks | I6: UK | J6: 6 | K6: Bank Transfer | L6: $76.00 | M6: =VLOOKUP(E6,Price!$A$2:$C$9,3,) -> $39.00 | N6: =J6 * VALUE(SUBSTITUTE(L6,"$","")) -> 456 | O6: =J6*VALUE(SUBSTITUTE(M6,"$","")) -> 234 | P6: =N6-O6 -> 222 | Q6: =Table1[[#This Row],[Profit ]]/Table1[[#This Row],[Total Revenue]] -> 0.48684211
A7: 46359 | B7: =RIGHT(TRIM(A7), 4) -> 6359 | C7: =MID(TRIM(A7), 4, 2) -> 59 | D7: =TEXT(DATE(RIGHT(TRIM(A7), 4), LEFT(TRIM(A7), 2), MID(TRIM(A7), 4, 2)), "mmm") -> Nov | E7: Canvas | F7: Utility | G7: Blue | H7: Nike | I7: Ghana | J7: 6 | K7: Card | L7: $128.00 | M7: =VLOOKUP(E7,Price!$A$2:$C$9,3,) -> $72.00 | N7: =J7 * VALUE(SUBSTITUTE(L7,"$","")) -> 768 | O7: =J7*VALUE(SUBSTITUTE(M7,"$","")) -> 432 | P7: =N7-O7 -> 336 | Q7: =Table1[[#This Row],[Profit ]]/Table1[[#This Row],[Total Revenue]] -> 0.4375
A8: 06/18/2026 | B8: =RIGHT(TRIM(A8), 4) -> 2026 | C8: =MID(TRIM(A8), 4, 2) -> 18 | D8: =TEXT(DATE(RIGHT(TRIM(A8), 4), LEFT(TRIM(A8), 2), MID(TRIM(A8), 4, 2)), "mmm") -> Jun | E8: Canvas | F8: Formal | G8: Green | H8: Clarks | I8: USA | J8: 13 | K8: Cash | L8: $128.00 | M8: =VLOOKUP(E8,Price!$A$2:$C$9,3,) -> $72.00 | N8: =J8 * VALUE(SUBSTITUTE(L8,"$","")) -> 1664 | O8: =J8*VALUE(SUBSTITUTE(M8,"$","")) -> 936 | P8: =N8-O8 -> 728 | Q8: =Table1[[#This Row],[Profit ]]/Table1[[#This Row],[Total Revenue]] -> 0.4375
A9: 46272 | B9: =RIGHT(TRIM(A9), 4) -> 6272 | C9: =MID(TRIM(A9), 4, 2) -> 72 | D9: =TEXT(DATE(RIGHT(TRIM(A9), 4), LEFT(TRIM(A9), 2), MID(TRIM(A9), 4, 2)), "mmm") -> Dec | E9: Monk Straps | F9: Formal | G9: Brown | H9: Timberland | I9: USA | J9: 12 | K9: Cash | L9: $89.00 | M9: =VLOOKUP(E9,Price!$A$2:$C$9,3,) -> $47.00 | N9: =J9 * VALUE(SUBSTITUTE(L9,"$","")) -> 1068 | O9: =J9*VALUE(SUBSTITUTE(M9,"$","")) -> 564 | P9: =N9-O9 -> 504 | Q9: =Table1[[#This Row],[Profit ]]/Table1[[#This Row],[Total Revenue]] -> 0.47191011
A10: 01/16/2026 | B10: =RIGHT(TRIM(A10), 4) -> 2026 | C10: =MID(TRIM(A10), 4, 2) -> 16 | D10: =TEXT(DATE(RIGHT(TRIM(A10), 4), LEFT(TRIM(A10), 2), MID(TRIM(A10), 4, 2)), "mmm") -> Jan | E10: Derby | F10: Formal | G10: Green | H10: Clarks | I10: Australia | J10: 10 | K10: Cash | L10: $32.00 | M10: =VLOOKUP(E10,Price!$A$2:$C$9,3,) -> $14.00 | N10: =J10 * VALUE(SUBSTITUTE(L10,"$","")) -> 320 | O10: =J10*VALUE(SUBSTITUTE(M10,"$","")) -> 140 | P10: =N10-O10 -> 180 | Q10: =Table1[[#This Row],[Profit ]]/Table1[[#This Row],[Total Revenue]] -> 0.5625
A11: 46271 | B11: =RIGHT(TRIM(A11), 4) -> 6271 | C11: =MID(TRIM(A11), 4, 2) -> 71 | D11: =TEXT(DATE(RIGHT(TRIM(A11), 4), LEFT(TRIM(A11), 2), MID(TRIM(A11), 4, 2)), "mmm") -> Dec | E11: Oxford | F11: Formal | G11: Black | H11: Clarks | I11: Cyprus | J11: 15 | K11: Mobile Money | L11: $105.00 | M11: =VLOOKUP(E11,Price!$A$2:$C$9,3,) -> $58.00 | N11: =J11 * VALUE(SUBSTITUTE(L11,"$","")) -> 1575 | O11: =J11*VALUE(SUBSTITUTE(M11,"$","")) -> 870 | P11: =N11-O11 -> 705 | Q11: =Table1[[#This Row],[Profit ]]/Table1[[#This Row],[Total Revenue]] -> 0.44761905
A12: 04/20/2026 | B12: =RIGHT(TRIM(A12), 4) -> 2026 | C12: =MID(TRIM(A12), 4, 2) -> 20 | D12: =TEXT(DATE(RIGHT(TRIM(A12), 4), LEFT(TRIM(A12), 2), MID(TRIM(A12), 4, 2)), "mmm") -> Apr | E12: Boots | F12: Formal | G12: Brown | H12: Clarks | I12: India | J12: 8 | K12: Bank Transfer | L12: $76.00 | M12: =VLOOKUP(E12,Price!$A$2:$C$9,3,) -> $39.00 | N12: =J12 * VALUE(SUBSTITUTE(L12,"$","")) -> 608 | O12: =J12*VALUE(SUBSTITUTE(M12,"$","")) -> 312 | P12: =N12-O12 -> 296 | Q12: =Table1[[#This Row],[Profit ]]/Table1[[#This Row],[Total Revenue]] -> 0.48684211
A13: 03/16/2026 | B13: =RIGHT(TRIM(A13), 4) -> 2026 | C13: =MID(TRIM(A13), 4, 2) -> 16 | D13: =TEXT(DATE(RIGHT(TRIM(A13), 4), LEFT(TRIM(A13), 2), MID(TRIM(A13), 4, 2)), "mmm") -> Mar | E13: Loafers | F13: Casual | G13: Green | H13: Clarks | I13: Australia | J13: 9 | K13: Cash | L13: $54.00 | M13: =VLOOKUP(E13,Price!$A$2:$C$9,3,) -> $28.00 | N13: =J13 * VALUE(SUBSTITUTE(L13,"$","")) -> 486 | O13: =J13*VALUE(SUBSTITUTE(M13,"$","")) -> 252 | P13: =N13-O13 -> 234 | Q13: =Table1[[#This Row],[Profit ]]/Table1[[#This Row],[Total Revenue]] -> 0.48148148
A14: 46117 | B14: =RIGHT(TRIM(A14), 4) -> 6117 | C14: =MID(TRIM(A14), 4, 2) -> 17 | D14: =TEXT(DATE(RIGHT(TRIM(A14), 4), LEFT(TRIM(A14), 2), MID(TRIM(A14), 4, 2)), "mmm") -> Oct | E14: Brogues | F14: Utility | G14: Green | H14: Nike | I14: Germany | J14: 14 | K14: Bank Transfer | L14: $112.00 | M14: =VLOOKUP(E14,Price!$A$2:$C$9,3,) -> $64.00 | N14: =J14 * VALUE(SUBSTITUTE(L14,"$","")) -> 1568 | O14: =J14*VALUE(SUBSTITUTE(M14,"$","")) -> 896 | P14: =N14-O14 -> 672 | Q14: =Table1[[#This Row],[Profit ]]/Table1[[#This Row],[Total Revenue]] -> 0.42857143
A15: 46266 | B15: =RIGHT(TRIM(A15), 4) -> 6266 | C15: =MID(TRIM(A15), 4, 2) -> 66 | D15: =TEXT(DATE(RIGHT(TRIM(A15), 4), LEFT(TRIM(A15), 2), MID(TRIM(A15), 4, 2)), "mmm") -> Dec | E15: Oxford | F15: Formal | G15: Green | H15: Timberland | I15: Nigeria | J15: 4 | K15: Card | L15: $105.00 | M15: =VLOOKUP(E15,Price!$A$2:$C$9,3,) -> $58.00 | N15: =J15 * VALUE(SUBSTITUTE(L15,"$","")) -> 420 | O15: =J15*VALUE(SUBSTITUTE(M15,"$","")) -> 232 | P15: =N15-O15 -> 188 | Q15: =Table1[[#This Row],[Profit ]]/Table1[[#This Row],[Total Revenue]] -> 0.44761905
A16: 06/26/2026 | B16: =RIGHT(TRIM(A16), 4) -> 2026 | C16: =MID(TRIM(A16), 4, 2) -> 26 | D16: =TEXT(DATE(RIGHT(TRIM(A16), 4), LEFT(TRIM(A16), 2), MID(TRIM(A16), 4, 2)), "mmm") -> Jun | E16: Slippers | F16: Formal | G16: Red | H16: Zara | I16: Uganda | J16: 6 | K16: Card | L16: $119.00 | M16: =VLOOKUP(E16,Price!$A$2:$C$9,3,) -> $67.00 | N16: =J16 * VALUE(SUBSTITUTE(L16,"$","")) -> 714 | O16: =J16*VALUE(SUBSTITUTE(M16,"$","")) -> 402 | P16: =N16-O16 -> 312 | Q16: =Table1[[#This Row],[Profit ]]/Table1[[#This Row],[Total Revenue]] -> 0.43697479
A17: 07/23/2026 | B17: =RIGHT(TRIM(A17), 4) -> 2026 | C17: =MID(TRIM(A17), 4, 2) -> 23 | D17: =TEXT(DATE(RIGHT(TRIM(A17), 4), LEFT(TRIM(A17), 2), MID(TRIM(A17), 4, 2)), "mmm") -> Jul | E17: Derby | F17: Casual | G17: Green | H17: Zara | I17: Philippines | J17: 10 | K17: Cash | L17: $32.00 | M17: =VLOOKUP(E17,Price!$A$2:$C$9,3,) -> $14.00 | N17: =J17 * VALUE(SUBSTITUTE(L17,"$","")) -> 320 | O17: =J17*VALUE(SUBSTITUTE(M17,"$","")) -> 140 | P17: =N17-O17 -> 180 | Q17: =Table1[[#This Row],[Profit ]]/Table1[[#This Row],[Total Revenue]] -> 0.5625
A18: 04/13/2026 | B18: =RIGHT(TRIM(A18), 4) -> 2026 | C18: =MID(TRIM(A18), 4, 2) -> 13 | D18: =TEXT(DATE(RIGHT(TRIM(A18), 4), LEFT(TRIM(A18), 2), MID(TRIM(A18), 4, 2)), "mmm") -> Apr | E18: Boots | F18: Open | G18: Red | H18: Steve Madden | I18: Nigeria | J18: 7 | K18: Bank Transfer | L18: $76.00 | M18: =VLOOKUP(E18,Price!$A$2:$C$9,3,) -> $39.00 | N18: =J18 * VALUE(SUBSTITUTE(L18,"$","")) -> 532 | O18: =J18*VALUE(SUBSTITUTE(M18,"$","")) -> 273 | P18: =N18-O18 -> 259 | Q18: =Table1[[#This Row],[Profit ]]/Table1[[#This Row],[Total Revenue]] -> 0.48684211
A19: 05/20/2026 | B19: =RIGHT(TRIM(A19), 4) -> 2026 | C19: =MID(TRIM(A19), 4, 2) -> 20 | D19: =TEXT(DATE(RIGHT(TRIM(A19), 4), LEFT(TRIM(A19), 2), MID(TRIM(A19), 4, 2)), "mmm") -> May | E19: Derby | F19: Casual | G19: Blue | H19: Clarks | I19: UK | J19: 7 | K19: Mobile Money | L19: $32.00 | M19: =VLOOKUP(E19,Price!$A$2:$C$9,3,) -> $14.00 | N19: =J19 * VALUE(SUBSTITUTE(L19,"$","")) -> 224 | O19: =J19*VALUE(SUBSTITUTE(M19,"$","")) -> 98 | P19: =N19-O19 -> 126 | Q19: =Table1[[#This Row],[Profit ]]/Table1[[#This Row],[Total Revenue]] -> 0.5625
A20: 03/31/2026 | B20: =RIGHT(TRIM(A20), 4) -> 2026 | C20: =MID(TRIM(A20), 4, 2) -> 31 | D20: =TEXT(DATE(RIGHT(TRIM(A20), 4), LEFT(TRIM(A20), 2), MID(TRIM(A20), 4, 2)), "mmm") -> Mar | E20: Oxford | F20: Open | G20: Black | H20: Clarks | I20: UK | J20: 11 | K20: Cash | L20: $105.00 | M20: =VLOOKUP(E20,Price!$A$2:$C$9,3,) -> $58.00 | N20: =J20 * VALUE(SUBSTITUTE(L20,"$","")) -> 1155 | O20: =J20*VALUE(SUBSTITUTE(M20,"$","")) -> 638 | P20: =N20-O20 -> 517 | Q20: =Table1[[#This Row],[Profit ]]/Table1[[#This Row],[Total Revenue]] -> 0.44761905
A21: 46147 | B21: =RIGHT(TRIM(A21), 4) -> 6147 | C21: =MID(TRIM(A21), 4, 2) -> 47 | D21: =TEXT(DATE(RIGHT(TRIM(A21), 4), LEFT(TRIM(A21), 2), MID(TRIM(A21), 4, 2)), "mmm") -> Nov | E21: Boots | F21: Utility | G21: Red | H21: Nike | I21: Zimbabwe | J21: 6 | K21: Cash | L21: $76.00 | M21: =VLOOKUP(E21,Price!$A$2:$C$9,3,) -> $39.00 | N21: =J21 * VALUE(SUBSTITUTE(L21,"$","")) -> 456 | O21: =J21*VALUE(SUBSTITUTE(M21,"$","")) -> 234 | P21: =N21-O21 -> 222 | Q21: =Table1[[#This Row],[Profit ]]/Table1[[#This Row],[Total Revenue]] -> 0.48684211
A22: 46211 | B22: =RIGHT(TRIM(A22), 4) -> 6211 | C22: =MID(TRIM(A22), 4, 2) -> 11 | D22: =TEXT(DATE(RIGHT(TRIM(A22), 4), LEFT(TRIM(A22), 2), MID(TRIM(A22), 4, 2)), "mmm") -> Oct | E22: Monk Straps | F22: Formal | G22: Red | H22: Clarks | I22: Germany | J22: 8 | K22: Card | L22: $89.00 | M22: =VLOOKUP(E22,Price!$A$2:$C$9,3,) -> $47.00 | N22: =J22 * VALUE(SUBSTITUTE(L22,"$","")) -> 712 | O22: =J22*VALUE(SUBSTITUTE(M22,"$","")) -> 376 | P22: =N22-O22 -> 336 | Q22: =Table1[[#This Row],[Profit ]]/Table1[[#This Row],[Total Revenue]] -> 0.47191011
A23: 07/14/2026 | B23: =RIGHT(TRIM(A23), 4) -> 2026 | C23: =MID(TRIM(A23), 4, 2) -> 14 | D23: =TEXT(DATE(RIGHT(TRIM(A23), 4), LEFT(TRIM(A23), 2), MID(TRIM(A23), 4, 2)), "mmm") -> Jul | E23: Brogues | F23: Casual | G23: Green | H23: Steve Madden | I23: Australia | J23: 5 | K23: Mobile Money | L23: $112.00 | M23: =VLOOKUP(E23,Price!$A$2:$C$9,3,) -> $64.00 | N23: =J23 * VALUE(SUBSTITUTE(L23,"$","")) -> 560 | O23: =J23*VALUE(SUBSTITUTE(M23,"$","")) -> 320 | P23: =N23-O23 -> 240 | Q23: =Table1[[#This Row],[Profit ]]/Table1[[#This Row],[Total Revenue]] -> 0.42857143
A24: 46357 | B24: =RIGHT(TRIM(A24), 4) -> 6357 | C24: =MID(TRIM(A24), 4, 2) -> 57 | D24: =TEXT(DATE(RIGHT(TRIM(A24), 4), LEFT(TRIM(A24), 2), MID(TRIM(A24), 4, 2)), "mmm") -> Nov | E24: Oxford | F24: Formal | G24: Green | H24: Steve Madden | I24: Zimbabwe | J24: 15 | K24: Card | L24: $105.00 | M24: =VLOOKUP(E24,Price!$A$2:$C$9,3,) -> $58.00 | N24: =J24 * VALUE(SUBSTITUTE(L24,"$","")) -> 1575 | O24: =J24*VALUE(SUBSTITUTE(M24,"$","")) -> 870 | P24: =N24-O24 -> 705 | Q24: =Table1[[#This Row],[Profit ]]/Table1[[#This Row],[Total Revenue]] -> 0.44761905
A25: 01/28/2026 | B25: =RIGHT(TRIM(A25), 4) -> 2026 | C25: =MID(TRIM(A25), 4, 2) -> 28 | D25: =TEXT(DATE(RIGHT(TRIM(A25), 4), LEFT(TRIM(A25), 2), MID(TRIM(A25), 4, 2)), "mmm") -> Jan | E25: Canvas | F25: Formal | G25: Green | H25: Steve Madden | I25: Cyprus | J25: 1 | K25: Card | L25: $128.00 | M25: =VLOOKUP(E25,Price!$A$2:$C$9,3,) -> $72.00 | N25: =J25 * VALUE(SUBSTITUTE(L25,"$","")) -> 128 | O25: =J25*VALUE(SUBSTITUTE(M25,"$","")) -> 72 | P25: =N25-O25 -> 56 | Q25: =Table1[[#This Row],[Profit ]]/Table1[[#This Row],[Total Revenue]] -> 0.4375
A26: 01/13/2026 | B26: =RIGHT(TRIM(A26), 4) -> 2026 | C26: =MID(TRIM(A26), 4, 2) -> 13 | D26: =TEXT(DATE(RIGHT(TRIM(A26), 4), LEFT(TRIM(A26), 2), MID(TRIM(A26), 4, 2)), "mmm") -> Jan | E26: Boots | F26: Casual | G26: Blue | H26: Clarks | I26: Ghana | J26: 12 | K26: Cash | L26: $76.00 | M26: =VLOOKUP(E26,Price!$A$2:$C$9,3,) -> $39.00 | N26: =J26 * VALUE(SUBSTITUTE(L26,"$","")) -> 912 | O26: =J26*VALUE(SUBSTITUTE(M26,"$","")) -> 468 | P26: =N26-O26 -> 444 | Q26: =Table1[[#This Row],[Profit ]]/Table1[[#This Row],[Total Revenue]] -> 0.48684211
A27: 03/13/2026 | B27: =RIGHT(TRIM(A27), 4) -> 2026 | C27: =MID(TRIM(A27), 4, 2) -> 13 | D27: =TEXT(DATE(RIGHT(TRIM(A27), 4), LEFT(TRIM(A27), 2), MID(TRIM(A27), 4, 2)), "mmm") -> Mar | E27: Loafers | F27: Utility | G27: Green | H27: Steve Madden | I27: India | J27: 9 | K27: Mobile Money | L27: $54.00 | M27: =VLOOKUP(E27,Price!$A$2:$C$9,3,) -> $28.00 | N27: =J27 * VALUE(SUBSTITUTE(L27,"$","")) -> 486 | O27: =J27*VALUE(SUBSTITUTE(M27,"$","")) -> 252 | P27: =N27-O27 -> 234 | Q27: =Table1[[#This Row],[Profit ]]/Table1[[#This Row],[Total Revenue]] -> 0.48148148
A28: 46333 | B28: =RIGHT(TRIM(A28), 4) -> 6333 | C28: =MID(TRIM(A28), 4, 2) -> 33 | D28: =TEXT(DATE(RIGHT(TRIM(A28), 4), LEFT(TRIM(A28), 2), MID(TRIM(A28), 4, 2)), "mmm") -> Nov | E28: Oxford | F28: Formal | G28: Green | H28: Clarks | I28: Ghana | J28: 5 | K28: Mobile Money | L28: $105.00 | M28: =VLOOKUP(E28,Price!$A$2:$C$9,3,) -> $58.00 | N28: =J28 * VALUE(SUBSTITUTE(L28,"$","")) -> 525 | O28: =J28*VALUE(SUBSTITUTE(M28,"$","")) -> 290 | P28: =N28-O28 -> 235 | Q28: =Table1[[#This Row],[Profit ]]/Table1[[#This Row],[Total Revenue]] -> 0.44761905
A29: 46298 | B29: =RIGHT(TRIM(A29), 4) -> 6298 | C29: =MID(TRIM(A29), 4, 2) -> 98 | D29: =TEXT(DATE(RIGHT(TRIM(A29), 4), LEFT(TRIM(A29), 2), MID(TRIM(A29), 4, 2)), "mmm") -> Jan | E29: Loafers | F29: Casual | G29: Green | H29: Clarks | I29: Zimbabwe | J29: 8 | K29: Bank Transfer | L29: $54.00 | M29: =VLOOKUP(E29,Price!$A$2:$C$9,3,) -> $28.00 | N29: =J29 * VALUE(SUBSTITUTE(L29,"$","")) -> 432 | O29: =J29*VALUE(SUBSTITUTE(M29,"$","")) -> 224 | P29: =N29-O29 -> 208 | Q29: =Table1[[#This Row],[Profit ]]/Table1[[#This Row],[Total Revenue]] -> 0.48148148
A30: 04/30/2026 | B30: =RIGHT(TRIM(A30), 4) -> 2026 | C30: =MID(TRIM(A30), 4, 2) -> 30 | D30: =TEXT(DATE(RIGHT(TRIM(A30), 4), LEFT(TRIM(A30), 2), MID(TRIM(A30), 4, 2)), "mmm") -> Apr | E30: Oxford | F30: Formal | G30: Red | H30: Zara | I30: Nigeria | J30: 2 | K30: Bank Transfer | L30: $105.00 | M30: =VLOOKUP(E30,Price!$A$2:$C$9,3,) -> $58.00 | N30: =J30 * VALUE(SUBSTITUTE(L30,"$","")) -> 210 | O30: =J30*VALUE(SUBSTITUTE(M30,"$","")) -> 116 | P30: =N30-O30 -> 94 | Q30: =Table1[[#This Row],[Profit ]]/Table1[[#This Row],[Total Revenue]] -> 0.44761905
A31: 02/15/2026 | B31: =RIGHT(TRIM(A31), 4) -> 2026 | C31: =MID(TRIM(A31), 4, 2) -> 15 | D31: =TEXT(DATE(RIGHT(TRIM(A31), 4), LEFT(TRIM(A31), 2), MID(TRIM(A31), 4, 2)), "mmm") -> Feb | E31: Monk Straps | F31: Formal | G31: Blue | H31: Zara | I31: Albania | J31: 7 | K31: Cash | L31: $89.00 | M31: =VLOOKUP(E31,Price!$A$2:$C$9,3,) -> $47.00 | N31: =J31 * VALUE(SUBSTITUTE(L31,"$","")) -> 623 | O31: =J31*VALUE(SUBSTITUTE(M31,"$","")) -> 329 | P31: =N31-O31 -> 294 | Q31: =Table1[[#This Row],[Profit ]]/Table1[[#This Row],[Total Revenue]] -> 0.47191011
A32: 07/16/2026 | B32: =RIGHT(TRIM(A32), 4) -> 2026 | C32: =MID(TRIM(A32), 4, 2) -> 16 | D32: =TEXT(DATE(RIGHT(TRIM(A32), 4), LEFT(TRIM(A32), 2), MID(TRIM(A32), 4, 2)), "mmm") -> Jul | E32: Brogues | F32: Formal | G32: Red | H32: Steve Madden | I32: Germany | J32: 12 | K32: Mobile Money | L32: $112.00 | M32: =VLOOKUP(E32,Price!$A$2:$C$9,3,) -> $64.00 | N32: =J32 * VALUE(SUBSTITUTE(L32,"$","")) -> 1344 | O32: =J32*VALUE(SUBSTITUTE(M32,"$","")) -> 768 | P32: =N32-O32 -> 576 | Q32: =Table1[[#This Row],[Profit ]]/Table1[[#This Row],[Total Revenue]] -> 0.42857143
A33: 46362 | B33: =RIGHT(TRIM(A33), 4) -> 6362 | C33: =MID(TRIM(A33), 4, 2) -> 62 | D33: =TEXT(DATE(RIGHT(TRIM(A33), 4), LEFT(TRIM(A33), 2), MID(TRIM(A33), 4, 2)), "mmm") -> Dec | E33: Canvas | F33: Formal | G33: Blue | H33: Clarks | I33: Zimbabwe | J33: 15 | K33: Card | L33: $128.00 | M33: =VLOOKUP(E33,Price!$A$2:$C$9,3,) -> $72.00 | N33: =J33 * VALUE(SUBSTITUTE(L33,"$","")) -> 1920 | O33: =J33*VALUE(SUBSTITUTE(M33,"$","")) -> 1080 | P33: =N33-O33 -> 840 | Q33: =Table1[[#This Row],[Profit ]]/Table1[[#This Row],[Total Revenue]] -> 0.4375
A34: 46061 | B34: =RIGHT(TRIM(A34), 4) -> 6061 | C34: =MID(TRIM(A34), 4, 2) -> 61 | D34: =TEXT(DATE(RIGHT(TRIM(A34), 4), LEFT(TRIM(A34), 2), MID(TRIM(A34), 4, 2)), "mmm") -> Nov | E34: Boots | F34: Formal | G34: Red | H34: Zara | I34: Uganda | J34: 7 | K34: Mobile Money | L34: $76.00 | M34: =VLOOKUP(E34,Price!$A$2:$C$9,3,) -> $39.00 | N34: =J34 * VALUE(SUBSTITUTE(L34,"$","")) -> 532 | O34: =J34*VALUE(SUBSTITUTE(M34,"$","")) -> 273 | P34: =N34-O34 -> 259 | Q34: =Table1[[#This Row],[Profit ]]/Table1[[#This Row],[Total Revenue]] -> 0.48684211
A35: 03/30/2026 | B35: =RIGHT(TRIM(A35), 4) -> 2026 | C35: =MID(TRIM(A35), 4, 2) -> 30 | D35: =TEXT(DATE(RIGHT(TRIM(A35), 4), LEFT(TRIM(A35), 2), MID(TRIM(A35), 4, 2)), "mmm") -> Mar | E35: Brogues | F35: Formal | G35: Black | H35: Nike | I35: Cyprus | J35: 10 | K35: Bank Transfer | L35: $112.00 | M35: =VLOOKUP(E35,Price!$A$2:$C$9,3,) -> $64.00 | N35: =J35 * VALUE(SUBSTITUTE(L35,"$","")) -> 1120 | O35: =J35*VALUE(SUBSTITUTE(M35,"$","")) -> 640 | P35: =N35-O35 -> 480 | Q35: =Table1[[#This Row],[Profit ]]/Table1[[#This Row],[Total Revenue]] -> 0.42857143
A36: 04/20/2026 | B36: =RIGHT(TRIM(A36), 4) -> 2026 | C36: =MID(TRIM(A36), 4, 2) -> 20 | D36: =TEXT(DATE(RIGHT(TRIM(A36), 4), LEFT(TRIM(A36), 2), MID(TRIM(A36), 4, 2)), "mmm") -> Apr | E36: Monk Straps | F36: Open | G36: Green | H36: Nike | I36: Philippines | J36: 7 | K36: Bank Transfer | L36: $89.00 | M36: =VLOOKUP(E36,Price!$A$2:$C$9,3,) -> $47.00 | N36: =J36 * VALUE(SUBSTITUTE(L36,"$","")) -> 623 | O36: =J36*VALUE(SUBSTITUTE(M36,"$","")) -> 329 | P36: =N36-O36 -> 294 | Q36: =Table1[[#This Row],[Profit ]]/Table1[[#This Row],[Total Revenue]] -> 0.47191011
A37: 07/25/2026 | B37: =RIGHT(TRIM(A37), 4) -> 2026 | C37: =MID(TRIM(A37), 4, 2) -> 25 | D37: =TEXT(DATE(RIGHT(TRIM(A37), 4), LEFT(TRIM(A37), 2), MID(TRIM(A37), 4, 2)), "mmm") -> Jul | E37: Boots | F37: Formal | G37: Red | H37: Timberland | I37: Canada | J37: 5 | K37: Card | L37: $76.00 | M37: =VLOOKUP(E37,Price!$A$2:$C$9,3,) -> $39.00 | N37: =J37 * VALUE(SUBSTITUTE(L37,"$","")) -> 380 | O37: =J37*VALUE(SUBSTITUTE(M37,"$","")) -> 195 | P37: =N37-O37 -> 185 | Q37: =Table1[[#This Row],[Profit ]]/Table1[[#This Row],[Total Revenue]] -> 0.48684211
A38: 46087 | B38: =RIGHT(TRIM(A38), 4) -> 6087 | C38: =MID(TRIM(A38), 4, 2) -> 87 | D38: =TEXT(DATE(RIGHT(TRIM(A38), 4), LEFT(TRIM(A38), 2), MID(TRIM(A38), 4, 2)), "mmm") -> Dec | E38: Boots | F38: Formal | G38: Red | H38: Clarks | I38: India | J38: 11 | K38: Bank Transfer | L38: $76.00 | M38: =VLOOKUP(E38,Price!$A$2:$C$9,3,) -> $39.00 | N38: =J38 * VALUE(SUBSTITUTE(L38,"$","")) -> 836 | O38: =J38*VALUE(SUBSTITUTE(M38,"$","")) -> 429 | P38: =N38-O38 -> 407 | Q38: =Table1[[#This Row],[Profit ]]/Table1[[#This Row],[Total Revenue]] -> 0.48684211
A39: 07/23/2026 | B39: =RIGHT(TRIM(A39), 4) -> 2026 | C39: =MID(TRIM(A39), 4, 2) -> 23 | D39: =TEXT(DATE(RIGHT(TRIM(A39), 4), LEFT(TRIM(A39), 2), MID(TRIM(A39), 4, 2)), "mmm") -> Jul | E39: Slippers | F39: Casual | G39: Red | H39: Zara | I39: Zimbabwe | J39: 10 | K39: Bank Transfer | L39: $119.00 | M39: =VLOOKUP(E39,Price!$A$2:$C$9,3,) -> $67.00 | N39: =J39 * VALUE(SUBSTITUTE(L39,"$","")) -> 1190 | O39: =J39*VALUE(SUBSTITUTE(M39,"$","")) -> 670 | P39: =N39-O39 -> 520 | Q39: =Table1[[#This Row],[Profit ]]/Table1[[#This Row],[Total Revenue]] -> 0.43697479
A40: 07/25/2026 | B40: =RIGHT(TRIM(A40), 4) -> 2026 | C40: =MID(TRIM(A40), 4, 2) -> 25 | D40: =TEXT(DATE(RIGHT(TRIM(A40), 4), LEFT(TRIM(A40), 2), MID(TRIM(A40), 4, 2)), "mmm") -> Jul | E40: Loafers | F40: Open | G40: Green | H40: Clarks | I40: USA | J40: 10 | K40: Mobile Money | L40: $54.00 | M40: =VLOOKUP(E40,Price!$A$2:$C$9,3,) -> $28.00 | N40: =J40 * VALUE(SUBSTITUTE(L40,"$","")) -> 540 | O40: =J40*VALUE(SUBSTITUTE(M40,"$","")) -> 280 | P40: =N40-O40 -> 260 | Q40: =Table1[[#This Row],[Profit ]]/Table1[[#This Row],[Total Revenue]] -> 0.48148148
A41: 46087 | B41: =RIGHT(TRIM(A41), 4) -> 6087 | C41: =MID(TRIM(A41), 4, 2) -> 87 | D41: =TEXT(DATE(RIGHT(TRIM(A41), 4), LEFT(TRIM(A41), 2), MID(TRIM(A41), 4, 2)), "mmm") -> Dec | E41: Oxford | F41: Formal | G41: Red | H41: Steve Madden | I41: Germany | J41: 13 | K41: Bank Transfer | L41: $105.00 | M41: =VLOOKUP(E41,Price!$A$2:$C$9,3,) -> $58.00 | N41: =J41 * VALUE(SUBSTITUTE(L41,"$","")) -> 1365 | O41: =J41*VALUE(SUBSTITUTE(M41,"$","")) -> 754 | P41: =N41-O41 -> 611 | Q41: =Table1[[#This Row],[Profit ]]/Table1[[#This Row],[Total Revenue]] -> 0.44761905
A42: 46268 | B42: =RIGHT(TRIM(A42), 4) -> 6268 | C42: =MID(TRIM(A42), 4, 2) -> 68 | D42: =TEXT(DATE(RIGHT(TRIM(A42), 4), LEFT(TRIM(A42), 2), MID(TRIM(A42), 4, 2)), "mmm") -> Dec | E42: Brogues | F42: Formal | G42: Blue | H42: Clarks | I42: USA | J42: 7 | K42: Cash | L42: $112.00 | M42: =VLOOKUP(E42,Price!$A$2:$C$9,3,) -> $64.00 | N42: =J42 * VALUE(SUBSTITUTE(L42,"$","")) -> 784 | O42: =J42*VALUE(SUBSTITUTE(M42,"$","")) -> 448 | P42: =N42-O42 -> 336 | Q42: =Table1[[#This Row],[Profit ]]/Table1[[#This Row],[Total Revenue]] -> 0.42857143
A43: 02/19/2026 | B43: =RIGHT(TRIM(A43), 4) -> 2026 | C43: =MID(TRIM(A43), 4, 2) -> 19 | D43: =TEXT(DATE(RIGHT(TRIM(A43), 4), LEFT(TRIM(A43), 2), MID(TRIM(A43), 4, 2)), "mmm") -> Feb | E43: Boots | F43: Open | G43: Green | H43: Nike | I43: Nigeria | J43: 14 | K43: Cash | L43: $76.00 | M43: =VLOOKUP(E43,Price!$A$2:$C$9,3,) -> $39.00 | N43: =J43 * VALUE(SUBSTITUTE(L43,"$","")) -> 1064 | O43: =J43*VALUE(SUBSTITUTE(M43,"$","")) -> 546 | P43: =N43-O43 -> 518 | Q43: =Table1[[#This Row],[Profit ]]/Table1[[#This Row],[Total Revenue]] -> 0.48684211
A44: 07/17/2026 | B44: =RIGHT(TRIM(A44), 4) -> 2026 | C44: =MID(TRIM(A44), 4, 2) -> 17 | D44: =TEXT(DATE(RIGHT(TRIM(A44), 4), LEFT(TRIM(A44), 2), MID(TRIM(A44), 4, 2)), "mmm") -> Jul | E44: Oxford | F44: Open | G44: Green | H44: Clarks | I44: Ghana | J44: 13 | K44: Mobile Money | L44: $105.00 | M44: =VLOOKUP(E44,Price!$A$2:$C$9,3,) -> $58.00 | N44: =J44 * VALUE(SUBSTITUTE(L44,"$","")) -> 1365 | O44: =J44*VALUE(SUBSTITUTE(M44,"$","")) -> 754 | P44: =N44-O44 -> 611 | Q44: =Table1[[#This Row],[Profit ]]/Table1[[#This Row],[Total Revenue]] -> 0.44761905
A45: 04/15/2026 | B45: =RIGHT(TRIM(A45), 4) -> 2026 | C45: =MID(TRIM(A45), 4, 2) -> 15 | D45: =TEXT(DATE(RIGHT(TRIM(A45), 4), LEFT(TRIM(A45), 2), MID(TRIM(A45), 4, 2)), "mmm") -> Apr | E45: Loafers | F45: Open | G45: Red | H45: Nike | I45: Philippines | J45: 3 | K45: Card | L45: $54.00 | M45: =VLOOKUP(E45,Price!$A$2:$C$9,3,) -> $28.00 | N45: =J45 * VALUE(SUBSTITUTE(L45,"$","")) -> 162 | O45: =J45*VALUE(SUBSTITUTE(M45,"$","")) -> 84 | P45: =N45-O45 -> 78 | Q45: =Table1[[#This Row],[Profit ]]/Table1[[#This Row],[Total Revenue]] -> 0.48148148
A46: 04/19/2026 | B46: =RIGHT(TRIM(A46), 4) -> 2026 | C46: =MID(TRIM(A46), 4, 2) -> 19 | D46: =TEXT(DATE(RIGHT(TRIM(A46), 4), LEFT(TRIM(A46), 2), MID(TRIM(A46), 4, 2)), "mmm") -> Apr | E46: Boots | F46: Formal | G46: Green | H46: Steve Madden | I46: UK | J46: 1 | K46: Bank Transfer | L46: $76.00 | M46: =VLOOKUP(E46,Price!$A$2:$C$9,3,) -> $39.00 | N46: =J46 * VALUE(SUBSTITUTE(L46,"$","")) -> 76 | O46: =J46*VALUE(SUBSTITUTE(M46,"$","")) -> 39 | P46: =N46-O46 -> 37 | Q46: =Table1[[#This Row],[Profit ]]/Table1[[#This Row],[Total Revenue]] -> 0.48684211
A47: 05/23/2026 | B47: =RIGHT(TRIM(A47), 4) -> 2026 | C47: =MID(TRIM(A47), 4, 2) -> 23 | D47: =TEXT(DATE(RIGHT(TRIM(A47), 4), LEFT(TRIM(A47), 2), MID(TRIM(A47), 4, 2)), "mmm") -> May | E47: Brogues | F47: Formal | G47: Red | H47: Clarks | I47: Germany | J47: 9 | K47: Mobile Money | L47: $112.00 | M47: =VLOOKUP(E47,Price!$A$2:$C$9,3,) -> $64.00 | N47: =J47 * VALUE(SUBSTITUTE(L47,"$","")) -> 1008 | O47: =J47*VALUE(SUBSTITUTE(M47,"$","")) -> 576 | P47: =N47-O47 -> 432 | Q47: =Table1[[#This Row],[Profit ]]/Table1[[#This Row],[Total Revenue]] -> 0.42857143
A48: 46089 | B48: =RIGHT(TRIM(A48), 4) -> 6089 | C48: =MID(TRIM(A48), 4, 2) -> 89 | D48: =TEXT(DATE(RIGHT(TRIM(A48), 4), LEFT(TRIM(A48), 2), MID(TRIM(A48), 4, 2)), "mmm") -> Dec | E48: Boots | F48: Formal | G48: Green | H48: Zara | I48: Albania | J48: 5 | K48: Mobile Money | L48: $76.00 | M48: =VLOOKUP(E48,Price!$A$2:$C$9,3,) -> $39.00 | N48: =J48 * VALUE(SUBSTITUTE(L48,"$","")) -> 380 | O48: =J48*VALUE(SUBSTITUTE(M48,"$","")) -> 195 | P48: =N48-O48 -> 185 | Q48: =Table1[[#This Row],[Profit ]]/Table1[[#This Row],[Total Revenue]] -> 0.48684211
A49: 46145 | B49: =RIGHT(TRIM(A49), 4) -> 6145 | C49: =MID(TRIM(A49), 4, 2) -> 45 | D49: =TEXT(DATE(RIGHT(TRIM(A49), 4), LEFT(TRIM(A49), 2), MID(TRIM(A49), 4, 2)), "mmm") -> Nov | E49: Oxford | F49: Casual | G49: Black | H49: Nike | I49: USA | J49: 11 | K49: Mobile Money | L49: $105.00 | M49: =VLOOKUP(E49,Price!$A$2:$C$9,3,) -> $58.00 | N49: =J49 * VALUE(SUBSTITUTE(L49,"$","")) -> 1155 | O49: =J49*VALUE(SUBSTITUTE(M49,"$","")) -> 638 | P49: =N49-O49 -> 517 | Q49: =Table1[[#This Row],[Profit ]]/Table1[[#This Row],[Total Revenue]] -> 0.44761905
A50: 03/29/2026 | B50: =RIGHT(TRIM(A50), 4) -> 2026 | C50: =MID(TRIM(A50), 4, 2) -> 29 | D50: =TEXT(DATE(RIGHT(TRIM(A50), 4), LEFT(TRIM(A50), 2), MID(TRIM(A50), 4, 2)), "mmm") -> Mar | E50: Loafers | F50: Formal | G50: Black | H50: Zara | I50: USA | J50: 6 | K50: Card | L50: $54.00 | M50: =VLOOKUP(E50,Price!$A$2:$C$9,3,) -> $28.00 | N50: =J50 * VALUE(SUBSTITUTE(L50,"$","")) -> 324 | O50: =J50*VALUE(SUBSTITUTE(M50,"$","")) -> 168 | P50: =N50-O50 -> 156 | Q50: =Table1[[#This Row],[Profit ]]/Table1[[#This Row],[Total Revenue]] -> 0.48148148
A51: 06/27/2026 | B51: =RIGHT(TRIM(A51), 4) -> 2026 | C51: =MID(TRIM(A51), 4, 2) -> 27 | D51: =TEXT(DATE(RIGHT(TRIM(A51), 4), LEFT(TRIM(A51), 2), MID(TRIM(A51), 4, 2)), "mmm") -> Jun | E51: Boots | F51: Utility | G51: Blue | H51: Zara | I51: Kenya | J51: 1 | K51: Mobile Money | L51: $76.00 | M51: =VLOOKUP(E51,Price!$A$2:$C$9,3,) -> $39.00 | N51: =J51 * VALUE(SUBSTITUTE(L51,"$","")) -> 76 | O51: =J51*VALUE(SUBSTITUTE(M51,"$","")) -> 39 | P51: =N51-O51 -> 37 | Q51: =Table1[[#This Row],[Profit ]]/Table1[[#This Row],[Total Revenue]] -> 0.48684211
A52: 46181 | B52: =RIGHT(TRIM(A52), 4) -> 6181 | C52: =MID(TRIM(A52), 4, 2) -> 81 | D52: =TEXT(DATE(RIGHT(TRIM(A52), 4), LEFT(TRIM(A52), 2), MID(TRIM(A52), 4, 2)), "mmm") -> Dec | E52: Canvas | F52: Casual | G52: Red | H52: Clarks | I52: Albania | J52: 4 | K52: Bank Transfer | L52: $128.00 | M52: =VLOOKUP(E52,Price!$A$2:$C$9,3,) -> $72.00 | N52: =J52 * VALUE(SUBSTITUTE(L52,"$","")) -> 512 | O52: =J52*VALUE(SUBSTITUTE(M52,"$","")) -> 288 | P52: =N52-O52 -> 224 | Q52: =Table1[[#This Row],[Profit ]]/Table1[[#This Row],[Total Revenue]] -> 0.4375
A53: 01/29/2026 | B53: =RIGHT(TRIM(A53), 4) -> 2026 | C53: =MID(TRIM(A53), 4, 2) -> 29 | D53: =TEXT(DATE(RIGHT(TRIM(A53), 4), LEFT(TRIM(A53), 2), MID(TRIM(A53), 4, 2)), "mmm") -> Jan | E53: Oxford | F53: Utility | G53: Black | H53: Clarks | I53: India | J53: 5 | K53: Cash | L53: $105.00 | M53: =VLOOKUP(E53,Price!$A$2:$C$9,3,) -> $58.00 | N53: =J53 * VALUE(SUBSTITUTE(L53,"$","")) -> 525 | O53: =J53*VALUE(SUBSTITUTE(M53,"$","")) -> 290 | P53: =N53-O53 -> 235 | Q53: =Table1[[#This Row],[Profit ]]/Table1[[#This Row],[Total Revenue]] -> 0.44761905
A54: 46145 | B54: =RIGHT(TRIM(A54), 4) -> 6145 | C54: =MID(TRIM(A54), 4, 2) -> 45 | D54: =TEXT(DATE(RIGHT(TRIM(A54), 4), LEFT(TRIM(A54), 2), MID(TRIM(A54), 4, 2)), "mmm") -> Nov | E54: Monk Straps | F54: Formal | G54: Black | H54: Zara | I54: Uganda | J54: 4 | K54: Card | L54: $89.00 | M54: =VLOOKUP(E54,Price!$A$2:$C$9,3,) -> $47.00 | N54: =J54 * VALUE(SUBSTITUTE(L54,"$","")) -> 356 | O54: =J54*VALUE(SUBSTITUTE(M54,"$","")) -> 188 | P54: =N54-O54 -> 168 | Q54: =Table1[[#This Row],[Profit ]]/Table1[[#This Row],[Total Revenue]] -> 0.47191011
A55: 02/16/2026 | B55: =RIGHT(TRIM(A55), 4) -> 2026 | C55: =MID(TRIM(A55), 4, 2) -> 16 | D55: =TEXT(DATE(RIGHT(TRIM(A55), 4), LEFT(TRIM(A55), 2), MID(TRIM(A55), 4, 2)), "mmm") -> Feb | E55: Brogues | F55: Formal | G55: Black | H55: Zara | I55: Nigeria | J55: 1 | K55: Mobile Money | L55: $112.00 | M55: =VLOOKUP(E55,Price!$A$2:$C$9,3,) -> $64.00 | N55: =J55 * VALUE(SUBSTITUTE(L55,"$","")) -> 112 | O55: =J55*VALUE(SUBSTITUTE(M55,"$","")) -> 64 | P55: =N55-O55 -> 48 | Q55: =Table1[[#This Row],[Profit ]]/Table1[[#This Row],[Total Revenue]] -> 0.42857143
A56: 03/28/2026 | B56: =RIGHT(TRIM(A56), 4) -> 2026 | C56: =MID(TRIM(A56), 4, 2) -> 28 | D56: =TEXT(DATE(RIGHT(TRIM(A56), 4), LEFT(TRIM(A56), 2), MID(TRIM(A56), 4, 2)), "mmm") -> Mar | E56: Canvas | F56: Formal | G56: Red | H56: Nike | I56: Zimbabwe | J56: 4 | K56: Bank Transfer | L56: $128.00 | M56: =VLOOKUP(E56,Price!$A$2:$C$9,3,) -> $72.00 | N56: =J56 * VALUE(SUBSTITUTE(L56,"$","")) -> 512 | O56: =J56*VALUE(SUBSTITUTE(M56,"$","")) -> 288 | P56: =N56-O56 -> 224 | Q56: =Table1[[#This Row],[Profit ]]/Table1[[#This Row],[Total Revenue]] -> 0.4375
A57: 46057 | B57: =RIGHT(TRIM(A57), 4) -> 6057 | C57: =MID(TRIM(A57), 4, 2) -> 57 | D57: =TEXT(DATE(RIGHT(TRIM(A57), 4), LEFT(TRIM(A57), 2), MID(TRIM(A57), 4, 2)), "mmm") -> Nov | E57: Monk Straps | F57: Casual | G57: Black | H57: Clarks | I57: Canada | J57: 5 | K57: Card | L57: $89.00 | M57: =VLOOKUP(E57,Price!$A$2:$C$9,3,) -> $47.00 | N57: =J57 * VALUE(SUBSTITUTE(L57,"$","")) -> 445 | O57: =J57*VALUE(SUBSTITUTE(M57,"$","")) -> 235 | P57: =N57-O57 -> 210 | Q57: =Table1[[#This Row],[Profit ]]/Table1[[#This Row],[Total Revenue]] -> 0.47191011
A58: 46059 | B58: =RIGHT(TRIM(A58), 4) -> 6059 | C58: =MID(TRIM(A58), 4, 2) -> 59 | D58: =TEXT(DATE(RIGHT(TRIM(A58), 4), LEFT(TRIM(A58), 2), MID(TRIM(A58), 4, 2)), "mmm") -> Nov | E58: Canvas | F58: Open | G58: Black | H58: Steve Madden | I58: Cyprus | J58: 2 | K58: Cash | L58: $128.00 | M58: =VLOOKUP(E58,Price!$A$2:$C$9,3,) -> $72.00 | N58: =J58 * VALUE(SUBSTITUTE(L58,"$","")) -> 256 | O58: =J58*VALUE(SUBSTITUTE(M58,"$","")) -> 144 | P58: =N58-O58 -> 112 | Q58: =Table1[[#This Row],[Profit ]]/Table1[[#This Row],[Total Revenue]] -> 0.4375
A59: 01/23/2026 | B59: =RIGHT(TRIM(A59), 4) -> 2026 | C59: =MID(TRIM(A59), 4, 2) -> 23 | D59: =TEXT(DATE(RIGHT(TRIM(A59), 4), LEFT(TRIM(A59), 2), MID(TRIM(A59), 4, 2)), "mmm") -> Jan | E59: Slippers | F59: Formal | G59: Red | H59: Nike | I59: Nigeria | J59: 1 | K59: Bank Transfer | L59: $119.00 | M59: =VLOOKUP(E59,Price!$A$2:$C$9,3,) -> $67.00 | N59: =J59 * VALUE(SUBSTITUTE(L59,"$","")) -> 119 | O59: =J59*VALUE(SUBSTITUTE(M59,"$","")) -> 67 | P59: =N59-O59 -> 52 | Q59: =Table1[[#This Row],[Profit ]]/Table1[[#This Row],[Total Revenue]] -> 0.43697479
A60: 07/27/2026 | B60: =RIGHT(TRIM(A60), 4) -> 2026 | C60: =MID(TRIM(A60), 4, 2) -> 27 | D60: =TEXT(DATE(RIGHT(TRIM(A60), 4), LEFT(TRIM(A60), 2), MID(TRIM(A60), 4, 2)), "mmm") -> Jul | E60: Brogues | F60: Casual | G60: Green | H60: Nike | I60: Uganda | J60: 15 | K60: Bank Transfer | L60: $112.00 | M60: =VLOOKUP(E60,Price!$A$2:$C$9,3,) -> $64.00 | N60: =J60 * VALUE(SUBSTITUTE(L60,"$","")) -> 1680 | O60: =J60*VALUE(SUBSTITUTE(M60,"$","")) -> 960 | P60: =N60-O60 -> 720 | Q60: =Table1[[#This Row],[Profit ]]/Table1[[#This Row],[Total Revenue]] -> 0.42857143
A61: 06/23/2026 | B61: =RIGHT(TRIM(A61), 4) -> 2026 | C61: =MID(TRIM(A61), 4, 2) -> 23 | D61: =TEXT(DATE(RIGHT(TRIM(A61), 4), LEFT(TRIM(A61), 2), MID(TRIM(A61), 4, 2)), "mmm") -> Jun | E61: Boots | F61: Formal | G61: Green | H61: Steve Madden | I61: UK | J61: 11 | K61: Mobile Money | L61: $76.00 | M61: =VLOOKUP(E61,Price!$A$2:$C$9,3,) -> $39.00 | N61: =J61 * VALUE(SUBSTITUTE(L61,"$","")) -> 836 | O61: =J61*VALUE(SUBSTITUTE(M61,"$","")) -> 429 | P61: =N61-O61 -> 407 | Q61: =Table1[[#This Row],[Profit ]]/Table1[[#This Row],[Total Revenue]] -> 0.48684211
A62: 46269 | B62: =RIGHT(TRIM(A62), 4) -> 6269 | C62: =MID(TRIM(A62), 4, 2) -> 69 | D62: =TEXT(DATE(RIGHT(TRIM(A62), 4), LEFT(TRIM(A62), 2), MID(TRIM(A62), 4, 2)), "mmm") -> Dec | E62: Oxford | F62: Utility | G62: Red | H62: Clarks | I62: Ghana | J62: 10 | K62: Card | L62: $105.00 | M62: =VLOOKUP(E62,Price!$A$2:$C$9,3,) -> $58.00 | N62: =J62 * VALUE(SUBSTITUTE(L62,"$","")) -> 1050 | O62: =J62*VALUE(SUBSTITUTE(M62,"$","")) -> 580 | P62: =N62-O62 -> 470 | Q62: =Table1[[#This Row],[Profit ]]/Table1[[#This Row],[Total Revenue]] -> 0.44761905
A63: 06/21/2026 | B63: =RIGHT(TRIM(A63), 4) -> 2026 | C63: =MID(TRIM(A63), 4, 2) -> 21 | D63: =TEXT(DATE(RIGHT(TRIM(A63), 4), LEFT(TRIM(A63), 2), MID(TRIM(A63), 4, 2)), "mmm") -> Jun | E63: Canvas | F63: Formal | G63: Brown | H63: Steve Madden | I63: Canada | J63: 9 | K63: Card | L63: $128.00 | M63: =VLOOKUP(E63,Price!$A$2:$C$9,3,) -> $72.00 | N63: =J63 * VALUE(SUBSTITUTE(L63,"$","")) -> 1152 | O63: =J63*VALUE(SUBSTITUTE(M63,"$","")) -> 648 | P63: =N63-O63 -> 504 | Q63: =Table1[[#This Row],[Profit ]]/Table1[[#This Row],[Total Revenue]] -> 0.4375
A64: 02/28/2026 | B64: =RIGHT(TRIM(A64), 4) -> 2026 | C64: =MID(TRIM(A64), 4, 2) -> 28 | D64: =TEXT(DATE(RIGHT(TRIM(A64), 4), LEFT(TRIM(A64), 2), MID(TRIM(A64), 4, 2)), "mmm") -> Feb | E64: Loafers | F64: Formal | G64: Blue | H64: Nike | I64: Uganda | J64: 1 | K64: Bank Transfer | L64: $54.00 | M64: =VLOOKUP(E64,Price!$A$2:$C$9,3,) -> $28.00 | N64: =J64 * VALUE(SUBSTITUTE(L64,"$","")) -> 54 | O64: =J64*VALUE(SUBSTITUTE(M64,"$","")) -> 28 | P64: =N64-O64 -> 26 | Q64: =Table1[[#This Row],[Profit ]]/Table1[[#This Row],[Total Revenue]] -> 0.48148148
A65: 06/24/2026 | B65: =RIGHT(TRIM(A65), 4) -> 2026 | C65: =MID(TRIM(A65), 4, 2) -> 24 | D65: =TEXT(DATE(RIGHT(TRIM(A65), 4), LEFT(TRIM(A65), 2), MID(TRIM(A65), 4, 2)), "mmm") -> Jun | E65: Oxford | F65: Formal | G65: Green | H65: Zara | I65: Cyprus | J65: 8 | K65: Bank Transfer | L65: $105.00 | M65: =VLOOKUP(E65,Price!$A$2:$C$9,3,) -> $58.00 | N65: =J65 * VALUE(SUBSTITUTE(L65,"$","")) -> 840 | O65: =J65*VALUE(SUBSTITUTE(M65,"$","")) -> 464 | P65: =N65-O65 -> 376 | Q65: =Table1[[#This Row],[Profit ]]/Table1[[#This Row],[Total Revenue]] -> 0.44761905
A66: 03/31/2026 | B66: =RIGHT(TRIM(A66), 4) -> 2026 | C66: =MID(TRIM(A66), 4, 2) -> 31 | D66: =TEXT(DATE(RIGHT(TRIM(A66), 4), LEFT(TRIM(A66), 2), MID(TRIM(A66), 4, 2)), "mmm") -> Mar | E66: Oxford | F66: Casual | G66: Green | H66: Steve Madden | I66: Germany | J66: 5 | K66: Bank Transfer | L66: $105.00 | M66: =VLOOKUP(E66,Price!$A$2:$C$9,3,) -> $58.00 | N66: =J66 * VALUE(SUBSTITUTE(L66,"$","")) -> 525 | O66: =J66*VALUE(SUBSTITUTE(M66,"$","")) -> 290 | P66: =N66-O66 -> 235 | Q66: =Table1[[#This Row],[Profit ]]/Table1[[#This Row],[Total Revenue]] -> 0.44761905
A67: 46360 | B67: =RIGHT(TRIM(A67), 4) -> 6360 | C67: =MID(TRIM(A67), 4, 2) -> 60 | D67: =TEXT(DATE(RIGHT(TRIM(A67), 4), LEFT(TRIM(A67), 2), MID(TRIM(A67), 4, 2)), "mmm") -> Nov | E67: Derby | F67: Casual | G67: Black | H67: Timberland | I67: Nigeria | J67: 14 | K67: Card | L67: $32.00 | M67: =VLOOKUP(E67,Price!$A$2:$C$9,3,) -> $14.00 | N67: =J67 * VALUE(SUBSTITUTE(L67,"$","")) -> 448 | O67: =J67*VALUE(SUBSTITUTE(M67,"$","")) -> 196 | P67: =N67-O67 -> 252 | Q67: =Table1[[#This Row],[Profit ]]/Table1[[#This Row],[Total Revenue]] -> 0.5625
A68: 05/19/2026 | B68: =RIGHT(TRIM(A68), 4) -> 2026 | C68: =MID(TRIM(A68), 4, 2) -> 19 | D68: =TEXT(DATE(RIGHT(TRIM(A68), 4), LEFT(TRIM(A68), 2), MID(TRIM(A68), 4, 2)), "mmm") -> May | E68: Monk Straps | F68: Open | G68: Brown | H68: Clarks | I68: UK | J68: 14 | K68: Mobile Money | L68: $89.00 | M68: =VLOOKUP(E68,Price!$A$2:$C$9,3,) -> $47.00 | N68: =J68 * VALUE(SUBSTITUTE(L68,"$","")) -> 1246 | O68: =J68*VALUE(SUBSTITUTE(M68,"$","")) -> 658 | P68: =N68-O68 -> 588 | Q68: =Table1[[#This Row],[Profit ]]/Table1[[#This Row],[Total Revenue]] -> 0.47191011
A69: 46174 | B69: =RIGHT(TRIM(A69), 4) -> 6174 | C69: =MID(TRIM(A69), 4, 2) -> 74 | D69: =TEXT(DATE(RIGHT(TRIM(A69), 4), LEFT(TRIM(A69), 2), MID(TRIM(A69), 4, 2)), "mmm") -> Dec | E69: Brogues | F69: Formal | G69: Black | H69: Clarks | I69: Zimbabwe | J69: 8 | K69: Mobile Money | L69: $112.00 | M69: =VLOOKUP(E69,Price!$A$2:$C$9,3,) -> $64.00 | N69: =J69 * VALUE(SUBSTITUTE(L69,"$","")) -> 896 | O69: =J69*VALUE(SUBSTITUTE(M69,"$","")) -> 512 | P69: =N69-O69 -> 384 | Q69: =Table1[[#This Row],[Profit ]]/Table1[[#This Row],[Total Revenue]] -> 0.42857143
A70: 46179 | B70: =RIGHT(TRIM(A70), 4) -> 6179 | C70: =MID(TRIM(A70), 4, 2) -> 79 | D70: =TEXT(DATE(RIGHT(TRIM(A70), 4), LEFT(TRIM(A70), 2), MID(TRIM(A70), 4, 2)), "mmm") -> Dec | E70: Loafers | F70: Formal | G70: Black | H70: Clarks | I70: Philippines | J70: 7 | K70: Bank Transfer | L70: $54.00 | M70: =VLOOKUP(E70,Price!$A$2:$C$9,3,) -> $28.00 | N70: =J70 * VALUE(SUBSTITUTE(L70,"$","")) -> 378 | O70: =J70*VALUE(SUBSTITUTE(M70,"$","")) -> 196 | P70: =N70-O70 -> 182 | Q70: =Table1[[#This Row],[Profit ]]/Table1[[#This Row],[Total Revenue]] -> 0.48148148
A71: 46271 | B71: =RIGHT(TRIM(A71), 4) -> 6271 | C71: =MID(TRIM(A71), 4, 2) -> 71 | D71: =TEXT(DATE(RIGHT(TRIM(A71), 4), LEFT(TRIM(A71), 2), MID(TRIM(A71), 4, 2)), "mmm") -> Dec | E71: Brogues | F71: Open | G71: Green | H71: Clarks | I71: Philippines | J71: 7 | K71: Mobile Money | L71: $112.00 | M71: =VLOOKUP(E71,Price!$A$2:$C$9,3,) -> $64.00 | N71: =J71 * VALUE(SUBSTITUTE(L71,"$","")) -> 784 | O71: =J71*VALUE(SUBSTITUTE(M71,"$","")) -> 448 | P71: =N71-O71 -> 336 | Q71: =Table1[[#This Row],[Profit ]]/Table1[[#This Row],[Total Revenue]] -> 0.42857143
A72: 46115 | B72: =RIGHT(TRIM(A72), 4) -> 6115 | C72: =MID(TRIM(A72), 4, 2) -> 15 | D72: =TEXT(DATE(RIGHT(TRIM(A72), 4), LEFT(TRIM(A72), 2), MID(TRIM(A72), 4, 2)), "mmm") -> Oct | E72: Monk Straps | F72: Formal | G72: Green | H72: Timberland | I72: Ghana | J72: 8 | K72: Cash | L72: $89.00 | M72: =VLOOKUP(E72,Price!$A$2:$C$9,3,) -> $47.00 | N72: =J72 * VALUE(SUBSTITUTE(L72,"$","")) -> 712 | O72: =J72*VALUE(SUBSTITUTE(M72,"$","")) -> 376 | P72: =N72-O72 -> 336 | Q72: =Table1[[#This Row],[Profit ]]/Table1[[#This Row],[Total Revenue]] -> 0.47191011
A73: 46302 | B73: =RIGHT(TRIM(A73), 4) -> 6302 | C73: =MID(TRIM(A73), 4, 2) -> 02 | D73: =TEXT(DATE(RIGHT(TRIM(A73), 4), LEFT(TRIM(A73), 2), MID(TRIM(A73), 4, 2)), "mmm") -> Oct | E73: Derby | F73: Casual | G73: Green | H73: Clarks | I73: UK | J73: 9 | K73: Mobile Money | L73: $32.00 | M73: =VLOOKUP(E73,Price!$A$2:$C$9,3,) -> $14.00 | N73: =J73 * VALUE(SUBSTITUTE(L73,"$","")) -> 288 | O73: =J73*VALUE(SUBSTITUTE(M73,"$","")) -> 126 | P73: =N73-O73 -> 162 | Q73: =Table1[[#This Row],[Profit ]]/Table1[[#This Row],[Total Revenue]] -> 0.5625
A74: 46237 | B74: =RIGHT(TRIM(A74), 4) -> 6237 | C74: =MID(TRIM(A74), 4, 2) -> 37 | D74: =TEXT(DATE(RIGHT(TRIM(A74), 4), LEFT(TRIM(A74), 2), MID(TRIM(A74), 4, 2)), "mmm") -> Nov | E74: Boots | F74: Formal | G74: Brown | H74: Zara | I74: UK | J74: 5 | K74: Card | L74: $76.00 | M74: =VLOOKUP(E74,Price!$A$2:$C$9,3,) -> $39.00 | N74: =J74 * VALUE(SUBSTITUTE(L74,"$","")) -> 380 | O74: =J74*VALUE(SUBSTITUTE(M74,"$","")) -> 195 | P74: =N74-O74 -> 185 | Q74: =Table1[[#This Row],[Profit ]]/Table1[[#This Row],[Total Revenue]] -> 0.48684211
A75: 46028 | B75: =RIGHT(TRIM(A75), 4) -> 6028 | C75: =MID(TRIM(A75), 4, 2) -> 28 | D75: =TEXT(DATE(RIGHT(TRIM(A75), 4), LEFT(TRIM(A75), 2), MID(TRIM(A75), 4, 2)), "mmm") -> Oct | E75: Boots | F75: Formal | G75: Blue | H75: Steve Madden | I75: Philippines | J75: 9 | K75: Cash | L75: $76.00 | M75: =VLOOKUP(E75,Price!$A$2:$C$9,3,) -> $39.00 | N75: =J75 * VALUE(SUBSTITUTE(L75,"$","")) -> 684 | O75: =J75*VALUE(SUBSTITUTE(M75,"$","")) -> 351 | P75: =N75-O75 -> 333 | Q75: =Table1[[#This Row],[Profit ]]/Table1[[#This Row],[Total Revenue]] -> 0.48684211
A76: 02/24/2026 | B76: =RIGHT(TRIM(A76), 4) -> 2026 | C76: =MID(TRIM(A76), 4, 2) -> 24 | D76: =TEXT(DATE(RIGHT(TRIM(A76), 4), LEFT(TRIM(A76), 2), MID(TRIM(A76), 4, 2)), "mmm") -> Feb | E76: Oxford | F76: Casual | G76: Brown | H76: Clarks | I76: Germany | J76: 7 | K76: Card | L76: $105.00 | M76: =VLOOKUP(E76,Price!$A$2:$C$9,3,) -> $58.00 | N76: =J76 * VALUE(SUBSTITUTE(L76,"$","")) -> 735 | O76: =J76*VALUE(SUBSTITUTE(M76,"$","")) -> 406 | P76: =N76-O76 -> 329 | Q76: =Table1[[#This Row],[Profit ]]/Table1[[#This Row],[Total Revenue]] -> 0.44761905
A77: 46178 | B77: =RIGHT(TRIM(A77), 4) -> 6178 | C77: =MID(TRIM(A77), 4, 2) -> 78 | D77: =TEXT(DATE(RIGHT(TRIM(A77), 4), LEFT(TRIM(A77), 2), MID(TRIM(A77), 4, 2)), "mmm") -> Dec | E77: Oxford | F77: Formal | G77: Green | H77: Clarks | I77: Uganda | J77: 13 | K77: Cash | L77: $105.00 | M77: =VLOOKUP(E77,Price!$A$2:$C$9,3,) -> $58.00 | N77: =J77 * VALUE(SUBSTITUTE(L77,"$","")) -> 1365 | O77: =J77*VALUE(SUBSTITUTE(M77,"$","")) -> 754 | P77: =N77-O77 -> 611 | Q77: =Table1[[#This Row],[Profit ]]/Table1[[#This Row],[Total Revenue]] -> 0.44761905
A78: 46144 | B78: =RIGHT(TRIM(A78), 4) -> 6144 | C78: =MID(TRIM(A78), 4, 2) -> 44 | D78: =TEXT(DATE(RIGHT(TRIM(A78), 4), LEFT(TRIM(A78), 2), MID(TRIM(A78), 4, 2)), "mmm") -> Nov | E78: Loafers | F78: Formal | G78: Blue | H78: Zara | I78: Ghana | J78: 8 | K78: Card | L78: $54.00 | M78: =VLOOKUP(E78,Price!$A$2:$C$9,3,) -> $28.00 | N78: =J78 * VALUE(SUBSTITUTE(L78,"$","")) -> 432 | O78: =J78*VALUE(SUBSTITUTE(M78,"$","")) -> 224 | P78: =N78-O78 -> 208 | Q78: =Table1[[#This Row],[Profit ]]/Table1[[#This Row],[Total Revenue]] -> 0.48148148
A79: 46084 | B79: =RIGHT(TRIM(A79), 4) -> 6084 | C79: =MID(TRIM(A79), 4, 2) -> 84 | D79: =TEXT(DATE(RIGHT(TRIM(A79), 4), LEFT(TRIM(A79), 2), MID(TRIM(A79), 4, 2)), "mmm") -> Dec | E79: Derby | F79: Casual | G79: Brown | H79: Timberland | I79: Philippines | J79: 11 | K79: Mobile Money | L79: $32.00 | M79: =VLOOKUP(E79,Price!$A$2:$C$9,3,) -> $14.00 | N79: =J79 * VALUE(SUBSTITUTE(L79,"$","")) -> 352 | O79: =J79*VALUE(SUBSTITUTE(M79,"$","")) -> 154 | P79: =N79-O79 -> 198 | Q79: =Table1[[#This Row],[Profit ]]/Table1[[#This Row],[Total Revenue]] -> 0.5625
A80: 04/21/2026 | B80: =RIGHT(TRIM(A80), 4) -> 2026 | C80: =MID(TRIM(A80), 4, 2) -> 21 | D80: =TEXT(DATE(RIGHT(TRIM(A80), 4), LEFT(TRIM(A80), 2), MID(TRIM(A80), 4, 2)), "mmm") -> Apr | E80: Brogues | F80: Formal | G80: Green | H80: Clarks | I80: Australia | J80: 11 | K80: Card | L80: $112.00 | M80: =VLOOKUP(E80,Price!$A$2:$C$9,3,) -> $64.00 | N80: =J80 * VALUE(SUBSTITUTE(L80,"$","")) -> 1232 | O80: =J80*VALUE(SUBSTITUTE(M80,"$","")) -> 704 | P80: =N80-O80 -> 528 | Q80: =Table1[[#This Row],[Profit ]]/Table1[[#This Row],[Total Revenue]] -> 0.42857143
A81: 07/16/2026 | B81: =RIGHT(TRIM(A81), 4) -> 2026 | C81: =MID(TRIM(A81), 4, 2) -> 16 | D81: =TEXT(DATE(RIGHT(TRIM(A81), 4), LEFT(TRIM(A81), 2), MID(TRIM(A81), 4, 2)), "mmm") -> Jul | E81: Slippers | F81: Formal | G81: Black | H81: Timberland | I81: Kenya | J81: 15 | K81: Card | L81: $119.00 | M81: =VLOOKUP(E81,Price!$A$2:$C$9,3,) -> $67.00 | N81: =J81 * VALUE(SUBSTITUTE(L81,"$","")) -> 1785 | O81: =J81*VALUE(SUBSTITUTE(M81,"$","")) -> 1005 | P81: =N81-O81 -> 780 | Q81: =Table1[[#This Row],[Profit ]]/Table1[[#This Row],[Total Revenue]] -> 0.43697479
A82: 46268 | B82: =RIGHT(TRIM(A82), 4) -> 6268 | C82: =MID(TRIM(A82), 4, 2) -> 68 | D82: =TEXT(DATE(RIGHT(TRIM(A82), 4), LEFT(TRIM(A82), 2), MID(TRIM(A82), 4, 2)), "mmm") -> Dec | E82: Canvas | F82: Casual | G82: Brown | H82: Zara | I82: Zimbabwe | J82: 10 | K82: Bank Transfer | L82: $128.00 | M82: =VLOOKUP(E82,Price!$A$2:$C$9,3,) -> $72.00 | N82: =J82 * VALUE(SUBSTITUTE(L82,"$","")) -> 1280 | O82: =J82*VALUE(SUBSTITUTE(M82,"$","")) -> 720 | P82: =N82-O82 -> 560 | Q82: =Table1[[#This Row],[Profit ]]/Table1[[#This Row],[Total Revenue]] -> 0.4375
A83: 46146 | B83: =RIGHT(TRIM(A83), 4) -> 6146 | C83: =MID(TRIM(A83), 4, 2) -> 46 | D83: =TEXT(DATE(RIGHT(TRIM(A83), 4), LEFT(TRIM(A83), 2), MID(TRIM(A83), 4, 2)), "mmm") -> Nov | E83: Boots | F83: Utility | G83: Brown | H83: Zara | I83: Cyprus | J83: 4 | K83: Bank Transfer | L83: $76.00 | M83: =VLOOKUP(E83,Price!$A$2:$C$9,3,) -> $39.00 | N83: =J83 * VALUE(SUBSTITUTE(L83,"$","")) -> 304 | O83: =J83*VALUE(SUBSTITUTE(M83,"$","")) -> 156 | P83: =N83-O83 -> 148 | Q83: =Table1[[#This Row],[Profit ]]/Table1[[#This Row],[Total Revenue]] -> 0.48684211
A84: 03/16/2026 | B84: =RIGHT(TRIM(A84), 4) -> 2026 | C84: =MID(TRIM(A84), 4, 2) -> 16 | D84: =TEXT(DATE(RIGHT(TRIM(A84), 4), LEFT(TRIM(A84), 2), MID(TRIM(A84), 4, 2)), "mmm") -> Mar | E84: Boots | F84: Casual | G84: Green | H84: Steve Madden | I84: India | J84: 7 | K84: Mobile Money | L84: $76.00 | M84: =VLOOKUP(E84,Price!$A$2:$C$9,3,) -> $39.00 | N84: =J84 * VALUE(SUBSTITUTE(L84,"$","")) -> 532 | O84: =J84*VALUE(SUBSTITUTE(M84,"$","")) -> 273 | P84: =N84-O84 -> 259 | Q84: =Table1[[#This Row],[Profit ]]/Table1[[#This Row],[Total Revenue]] -> 0.48684211
A85: 01/19/2026 | B85: =RIGHT(TRIM(A85), 4) -> 2026 | C85: =MID(TRIM(A85), 4, 2) -> 19 | D85: =TEXT(DATE(RIGHT(TRIM(A85), 4), LEFT(TRIM(A85), 2), MID(TRIM(A85), 4, 2)), "mmm") -> Jan | E85: Derby | F85: Utility | G85: Blue | H85: Steve Madden | I85: Albania | J85: 7 | K85: Cash | L85: $32.00 | M85: =VLOOKUP(E85,Price!$A$2:$C$9,3,) -> $14.00 | N85: =J85 * VALUE(SUBSTITUTE(L85,"$","")) -> 224 | O85: =J85*VALUE(SUBSTITUTE(M85,"$","")) -> 98 | P85: =N85-O85 -> 126 | Q85: =Table1[[#This Row],[Profit ]]/Table1[[#This Row],[Total Revenue]] -> 0.5625
A86: 06/14/2026 | B86: =RIGHT(TRIM(A86), 4) -> 2026 | C86: =MID(TRIM(A86), 4, 2) -> 14 | D86: =TEXT(DATE(RIGHT(TRIM(A86), 4), LEFT(TRIM(A86), 2), MID(TRIM(A86), 4, 2)), "mmm") -> Jun | E86: Boots | F86: Formal | G86: Green | H86: Zara | I86: Nigeria | J86: 13 | K86: Mobile Money | L86: $76.00 | M86: =VLOOKUP(E86,Price!$A$2:$C$9,3,) -> $39.00 | N86: =J86 * VALUE(SUBSTITUTE(L86,"$","")) -> 988 | O86: =J86*VALUE(SUBSTITUTE(M86,"$","")) -> 507 | P86: =N86-O86 -> 481 | Q86: =Table1[[#This Row],[Profit ]]/Table1[[#This Row],[Total Revenue]] -> 0.48684211
A87: 46058 | B87: =RIGHT(TRIM(A87), 4) -> 6058 | C87: =MID(TRIM(A87), 4, 2) -> 58 | D87: =TEXT(DATE(RIGHT(TRIM(A87), 4), LEFT(TRIM(A87), 2), MID(TRIM(A87), 4, 2)), "mmm") -> Nov | E87: Loafers | F87: Utility | G87: Green | H87: Timberland | I87: Albania | J87: 12 | K87: Bank Transfer | L87: $54.00 | M87: =VLOOKUP(E87,Price!$A$2:$C$9,3,) -> $28.00 | N87: =J87 * VALUE(SUBSTITUTE(L87,"$","")) -> 648 | O87: =J87*VALUE(SUBSTITUTE(M87,"$","")) -> 336 | P87: =N87-O87 -> 312 | Q87: =Table1[[#This Row],[Profit ]]/Table1[[#This Row],[Total Revenue]] -> 0.48148148
A88: 46114 | B88: =RIGHT(TRIM(A88), 4) -> 6114 | C88: =MID(TRIM(A88), 4, 2) -> 14 | D88: =TEXT(DATE(RIGHT(TRIM(A88), 4), LEFT(TRIM(A88), 2), MID(TRIM(A88), 4, 2)), "mmm") -> Oct | E88: Boots | F88: Casual | G88: Red | H88: Timberland | I88: Uganda | J88: 14 | K88: Cash | L88: $76.00 | M88: =VLOOKUP(E88,Price!$A$2:$C$9,3,) -> $39.00 | N88: =J88 * VALUE(SUBSTITUTE(L88,"$","")) -> 1064 | O88: =J88*VALUE(SUBSTITUTE(M88,"$","")) -> 546 | P88: =N88-O88 -> 518 | Q88: =Table1[[#This Row],[Profit ]]/Table1[[#This Row],[Total Revenue]] -> 0.48684211
A89: 02/14/2026 | B89: =RIGHT(TRIM(A89), 4) -> 2026 | C89: =MID(TRIM(A89), 4, 2) -> 14 | D89: =TEXT(DATE(RIGHT(TRIM(A89), 4), LEFT(TRIM(A89), 2), MID(TRIM(A89), 4, 2)), "mmm") -> Feb | E89: Oxford | F89: Formal | G89: Brown | H89: Clarks | I89: Albania | J89: 8 | K89: Cash | L89: $105.00 | M89: =VLOOKUP(E89,Price!$A$2:$C$9,3,) -> $58.00 | N89: =J89 * VALUE(SUBSTITUTE(L89,"$","")) -> 840 | O89: =J89*VALUE(SUBSTITUTE(M89,"$","")) -> 464 | P89: =N89-O89 -> 376 | Q89: =Table1[[#This Row],[Profit ]]/Table1[[#This Row],[Total Revenue]] -> 0.44761905
A90: 03/18/2026 | B90: =RIGHT(TRIM(A90), 4) -> 2026 | C90: =MID(TRIM(A90), 4, 2) -> 18 | D90: =TEXT(DATE(RIGHT(TRIM(A90), 4), LEFT(TRIM(A90), 2), MID(TRIM(A90), 4, 2)), "mmm") -> Mar | E90: Boots | F90: Formal | G90: Green | H90: Clarks | I90: Cyprus | J90: 3 | K90: Bank Transfer | L90: $76.00 | M90: =VLOOKUP(E90,Price!$A$2:$C$9,3,) -> $39.00 | N90: =J90 * VALUE(SUBSTITUTE(L90,"$","")) -> 228 | O90: =J90*VALUE(SUBSTITUTE(M90,"$","")) -> 117 | P90: =N90-O90 -> 111 | Q90: =Table1[[#This Row],[Profit ]]/Table1[[#This Row],[Total Revenue]] -> 0.48684211
A91: 46268 | B91: =RIGHT(TRIM(A91), 4) -> 6268 | C91: =MID(TRIM(A91), 4, 2) -> 68 | D91: =TEXT(DATE(RIGHT(TRIM(A91), 4), LEFT(TRIM(A91), 2), MID(TRIM(A91), 4, 2)), "mmm") -> Dec | E91: Derby | F91: Utility | G91: Black | H91: Steve Madden | I91: Ghana | J91: 8 | K91: Card | L91: $32.00 | M91: =VLOOKUP(E91,Price!$A$2:$C$9,3,) -> $14.00 | N91: =J91 * VALUE(SUBSTITUTE(L91,"$","")) -> 256 | O91: =J91*VALUE(SUBSTITUTE(M91,"$","")) -> 112 | P91: =N91-O91 -> 144 | Q91: =Table1[[#This Row],[Profit ]]/Table1[[#This Row],[Total Revenue]] -> 0.5625
A92: 03/30/2026 | B92: =RIGHT(TRIM(A92), 4) -> 2026 | C92: =MID(TRIM(A92), 4, 2) -> 30 | D92: =TEXT(DATE(RIGHT(TRIM(A92), 4), LEFT(TRIM(A92), 2), MID(TRIM(A92), 4, 2)), "mmm") -> Mar | E92: Slippers | F92: Utility | G92: Green | H92: Zara | I92: Ghana | J92: 14 | K92: Bank Transfer | L92: $119.00 | M92: =VLOOKUP(E92,Price!$A$2:$C$9,3,) -> $67.00 | N92: =J92 * VALUE(SUBSTITUTE(L92,"$","")) -> 1666 | O92: =J92*VALUE(SUBSTITUTE(M92,"$","")) -> 938 | P92: =N92-O92 -> 728 | Q92: =Table1[[#This Row],[Profit ]]/Table1[[#This Row],[Total Revenue]] -> 0.43697479
A93: 46029 | B93: =RIGHT(TRIM(A93), 4) -> 6029 | C93: =MID(TRIM(A93), 4, 2) -> 29 | D93: =TEXT(DATE(RIGHT(TRIM(A93), 4), LEFT(TRIM(A93), 2), MID(TRIM(A93), 4, 2)), "mmm") -> Oct | E93: Brogues | F93: Formal | G93: Green | H93: Steve Madden | I93: Nigeria | J93: 7 | K93: Mobile Money | L93: $112.00 | M93: =VLOOKUP(E93,Price!$A$2:$C$9,3,) -> $64.00 | N93: =J93 * VALUE(SUBSTITUTE(L93,"$","")) -> 784 | O93: =J93*VALUE(SUBSTITUTE(M93,"$","")) -> 448 | P93: =N93-O93 -> 336 | Q93: =Table1[[#This Row],[Profit ]]/Table1[[#This Row],[Total Revenue]] -> 0.42857143
A94: 46364 | B94: =RIGHT(TRIM(A94), 4) -> 6364 | C94: =MID(TRIM(A94), 4, 2) -> 64 | D94: =TEXT(DATE(RIGHT(TRIM(A94), 4), LEFT(TRIM(A94), 2), MID(TRIM(A94), 4, 2)), "mmm") -> Dec | E94: Loafers | F94: Utility | G94: Brown | H94: Clarks | I94: UK | J94: 5 | K94: Cash | L94: $54.00 | M94: =VLOOKUP(E94,Price!$A$2:$C$9,3,) -> $28.00 | N94: =J94 * VALUE(SUBSTITUTE(L94,"$","")) -> 270 | O94: =J94*VALUE(SUBSTITUTE(M94,"$","")) -> 140 | P94: =N94-O94 -> 130 | Q94: =Table1[[#This Row],[Profit ]]/Table1[[#This Row],[Total Revenue]] -> 0.48148148
A95: 46327 | B95: =RIGHT(TRIM(A95), 4) -> 6327 | C95: =MID(TRIM(A95), 4, 2) -> 27 | D95: =TEXT(DATE(RIGHT(TRIM(A95), 4), LEFT(TRIM(A95), 2), MID(TRIM(A95), 4, 2)), "mmm") -> Oct | E95: Oxford | F95: Formal | G95: Green | H95: Steve Madden | I95: Nigeria | J95: 14 | K95: Cash | L95: $105.00 | M95: =VLOOKUP(E95,Price!$A$2:$C$9,3,) -> $58.00 | N95: =J95 * VALUE(SUBSTITUTE(L95,"$","")) -> 1470 | O95: =J95*VALUE(SUBSTITUTE(M95,"$","")) -> 812 | P95: =N95-O95 -> 658 | Q95: =Table1[[#This Row],[Profit ]]/Table1[[#This Row],[Total Revenue]] -> 0.44761905
A96: 06/30/2026 | B96: =RIGHT(TRIM(A96), 4) -> 2026 | C96: =MID(TRIM(A96), 4, 2) -> 30 | D96: =TEXT(DATE(RIGHT(TRIM(A96), 4), LEFT(TRIM(A96), 2), MID(TRIM(A96), 4, 2)), "mmm") -> Jun | E96: Slippers | F96: Open | G96: Red | H96: Clarks | I96: USA | J96: 6 | K96: Cash | L96: $119.00 | M96: =VLOOKUP(E96,Price!$A$2:$C$9,3,) -> $67.00 | N96: =J96 * VALUE(SUBSTITUTE(L96,"$","")) -> 714 | O96: =J96*VALUE(SUBSTITUTE(M96,"$","")) -> 402 | P96: =N96-O96 -> 312 | Q96: =Table1[[#This Row],[Profit ]]/Table1[[#This Row],[Total Revenue]] -> 0.43697479
A97: 01/22/2026 | B97: =RIGHT(TRIM(A97), 4) -> 2026 | C97: =MID(TRIM(A97), 4, 2) -> 22 | D97: =TEXT(DATE(RIGHT(TRIM(A97), 4), LEFT(TRIM(A97), 2), MID(TRIM(A97), 4, 2)), "mmm") -> Jan | E97: Slippers | F97: Casual | G97: Red | H97: Nike | I97: Nigeria | J97: 7 | K97: Card | L97: $119.00 | M97: =VLOOKUP(E97,Price!$A$2:$C$9,3,) -> $67.00 | N97: =J97 * VALUE(SUBSTITUTE(L97,"$","")) -> 833 | O97: =J97*VALUE(SUBSTITUTE(M97,"$","")) -> 469 | P97: =N97-O97 -> 364 | Q97: =Table1[[#This Row],[Profit ]]/Table1[[#This Row],[Total Revenue]] -> 0.43697479
A98: 07/20/2026 | B98: =RIGHT(TRIM(A98), 4) -> 2026 | C98: =MID(TRIM(A98), 4, 2) -> 20 | D98: =TEXT(DATE(RIGHT(TRIM(A98), 4), LEFT(TRIM(A98), 2), MID(TRIM(A98), 4, 2)), "mmm") -> Jul | E98: Loafers | F98: Formal | G98: Green | H98: Clarks | I98: Canada | J98: 9 | K98: Bank Transfer | L98: $54.00 | M98: =VLOOKUP(E98,Price!$A$2:$C$9,3,) -> $28.00 | N98: =J98 * VALUE(SUBSTITUTE(L98,"$","")) -> 486 | O98: =J98*VALUE(SUBSTITUTE(M98,"$","")) -> 252 | P98: =N98-O98 -> 234 | Q98: =Table1[[#This Row],[Profit ]]/Table1[[#This Row],[Total Revenue]] -> 0.48148148
A99: 46177 | B99: =RIGHT(TRIM(A99), 4) -> 6177 | C99: =MID(TRIM(A99), 4, 2) -> 77 | D99: =TEXT(DATE(RIGHT(TRIM(A99), 4), LEFT(TRIM(A99), 2), MID(TRIM(A99), 4, 2)), "mmm") -> Dec | E99: Monk Straps | F99: Formal | G99: Blue | H99: Steve Madden | I99: Ghana | J99: 10 | K99: Card | L99: $89.00 | M99: =VLOOKUP(E99,Price!$A$2:$C$9,3,) -> $47.00 | N99: =J99 * VALUE(SUBSTITUTE(L99,"$","")) -> 890 | O99: =J99*VALUE(SUBSTITUTE(M99,"$","")) -> 470 | P99: =N99-O99 -> 420 | Q99: =Table1[[#This Row],[Profit ]]/Table1[[#This Row],[Total Revenue]] -> 0.47191011
A100: 46357 | B100: =RIGHT(TRIM(A100), 4) -> 6357 | C100: =MID(TRIM(A100), 4, 2) -> 57 | D100: =TEXT(DATE(RIGHT(TRIM(A100), 4), LEFT(TRIM(A100), 2), MID(TRIM(A100), 4, 2)), "mmm") -> Nov | E100: Brogues | F100: Casual | G100: Red | H100: Nike | I100: Zimbabwe | J100: 6 | K100: Card | L100: $112.00 | M100: =VLOOKUP(E100,Price!$A$2:$C$9,3,) -> $64.00 | N100: =J100 * VALUE(SUBSTITUTE(L100,"$","")) -> 672 | O100: =J100*VALUE(SUBSTITUTE(M100,"$","")) -> 384 | P100: =N100-O100 -> 288 | Q100: =Table1[[#This Row],[Profit ]]/Table1[[#This Row],[Total Revenue]] -> 0.42857143
...

Sheet Price
A1: Product | B1: Price | C1: Cost
A2: Monk Straps | B2: $89.00 | C2: $47.00
A3: Loafers | B3: $54.00 | C3: $28.00
A4: Derby | B4: $32.00 | C4: $14.00
A5: Boots | B5: $76.00 | C5: $39.00
A6: Canvas | B6: $128.00 | C6: $72.00
A7: Oxford | B7: $105.00 | C7: $58.00
A8: Brogues | B8: $112.00 | C8: $64.00
A9: Slippers | B9: $119.00 | C9: $67.00

Sheet Pivot_Table
B1: Overall Performance | K1: Products Profitability & Margin Performance
B3: Revenue | C3: Total Profit | D3: Total Profit Margin | E3: Total Quantity | K3: Product | L3: Total Profit | M3: % Actual_Margin
B4: 355048 | C4: 162335 | D4: 0.47075624 | E4: 4012 | K4: Derby | L4: 9396 | M4: 0.5625
K5: Boots | L5: 19980 | M5: 0.48684211
K6: Loafers | L6: 11778 | M6: 0.48148148
K7: Monk Straps | L7: 24150 | M7: 0.47191011
K8: Oxford | L8: 26367 | M8: 0.44761905
K9: Canvas | L9: 27776 | M9: 0.4375
K10: Slippers | L10: 17784 | M10: 0.43697479
K11: Brogues | L11: 25104 | M11: 0.42857143
B12: TOTAL REVENUE | D12: TOTAL PROFIT | E12: PROFIT MARGIN | G12: TOTAL UNITS | K12: Grand Total | L12: 162335 | M12: 0.45721987
B16: Performance Over Time | K16: Performance by Category & Brand
B18: Date | C18: Revenue | D18: Total Profit | K18: Category | L18: Revenue | M18: Total Profit
B19: Jan | C19: 26803 | D19: 12480 | K19: Casual | L19: 82917 | M19: 37753
B20: Feb | C20: 24097 | D20: 11060 | K20: Formal | L20: 179935 | M20: 82274
B21: Mar | C21: 27137 | D21: 12364 | K21: Open | L21: 53035 | M21: 24172
B22: Apr | C22: 28019 | D22: 12679 | K22: Utility | L22: 39161 | M22: 18136
B23: May | C23: 27142 | D23: 12359 | K23: Grand Total | L23: 355048 | M23: 162335
B24: Jun | C24: 38635 | D24: 17665
B25: Jul | C25: 34791 | D25: 15786
B26: Aug | C26: 1341 | D26: 594
B27: Sep | C27: 1493 | D27: 667 | K27: Top Countries by Revenue
B28: Oct | C28: 42974 | D28: 19633
B29: Nov | C29: 55985 | D29: 25778 | K29: Brand | L29: Revenue | M29: Total Profit
B30: Dec | C30: 46631 | D30: 21270 | K30: Casual | L30: 82917 | M30: 37753
B31: Grand Total | C31: 355048 | D31: 162335 | K31: Formal | L31: 179935 | M31: 82274
K32: Open | L32: 53035 | M32: 24172
K33: Utility | L33: 39161 | M33: 18136
K34: Grand Total | L34: 355048 | M34: 162335
B35: Revenue Generated by Product
B37: Product | C37: Revenue
B38: Derby | C38: 16704 | K38: Product vs. Payment Breakdown
B39: Loafers | C39: 24462
B40: Slippers | C40: 40698
B41: Boots | C41: 41040 | K41: Sum of Quantity | L41: Column Labels
B42: Monk Straps | C42: 51175 | K42: Product | L42: Bank Transfer | M42: Card | N42: Cash | O42: Mobile Money | P42: Grand Total
B43: Brogues | C43: 58576 | K43: Boots | L43: 145 | M43: 155 | N43: 110 | O43: 130 | P43: 540
B44: Oxford | C44: 58905 | K44: Brogues | L44: 155 | M44: 122 | N44: 126 | O44: 120 | P44: 523
B45: Canvas | C45: 63488 | K45: Canvas | L45: 174 | M45: 123 | N45: 148 | O45: 51 | P45: 496
B46: Grand Total | C46: 355048 | K46: Derby | L46: 114 | M46: 155 | N46: 143 | O46: 110 | P46: 522
K47: Loafers | L47: 149 | M47: 82 | N47: 100 | O47: 122 | P47: 453
K48: Monk Straps | L48: 97 | M48: 156 | N48: 199 | O48: 123 | P48: 575
K49: Oxford | L49: 125 | M49: 192 | N49: 150 | O49: 94 | P49: 561
K50: Slippers | L50: 84 | M50: 123 | N50: 73 | O50: 62 | P50: 342
K51: Grand Total | L51: 1043 | M51: 1108 | N51: 1049 | O51: 812 | P51: 4012

Sheet Dashboard
B2: Overall Performance | L2: Products Profitability & Margin Performance
B8: TOTAL REVENUE | D8: TOTAL PROFIT | F8: PROFIT MARGIN | H8: TOTAL UNITS
B12: Performance Over Time
L20: Performance by Category & Brand
B30: Revenue Generated by Product
L38: Top Countries by Revenue
B48: Revenue Generated by Product
L56: Product vs. Payment Breakdown
